Workbook

Sheet Methodology Overview
A1: THE World University Rankings — Teaching (29.5%) → Staff-to-Student Ratio (4.5%)
A2: Measures Learning Environment Quality via Academic Staff per Student | 4.5% of Total WUR Score
A4: # | B4: Component | C4: Description & Methodology | D4: Weight
A5: 1 | B5: Staff-to-Student Ratio Definition | C5: Number of academic staff (FTE) per student (FTE). THE computes this as: Academic Staff FTE ÷ Student FTE. A lower ratio (more staff per student) = better personal attention, mentorship, and teaching quality. THE inverts this for scoring: higher score for lower ratio. | D5: 4.5% of WUR
A6: 2 | B6: Academic Staff FTE | C6: Full-time equivalent count of academic and research staff. Per THE definition: professors, associate professors, assistant professors, lecturers, teaching fellows, research fellows WITH teaching duties. Excludes: administrative staff, technical staff, support staff, visiting faculty (unless FTE ≥ 0.5), and emeritus faculty without active teaching. | D6: Numerator
A7: 3 | B7: Student FTE | C7: Full-time equivalent student count. Includes all enrolled students: undergraduate, postgraduate (taught), postgraduate (research/PhD), professional programme students. Part-time students counted at pro-rata FTE (e.g., 0.5 FTE for half-time). Excludes: distance-only learners (unless specified), non-degree exchange students (short-term). | D7: Denominator
A8: 4 | B8: Context: Teaching Pillar | C8: Teaching (29.5%) = Teaching Reputation (15%) + Staff-to-Student Ratio (4.5%) + Doctorates Awarded per Staff (5.5%) + Doctorate-to-Bachelor's Ratio (2%) + Institutional Income (2.5%). Staff-to-student ratio is rated 🟡 Moderate difficulty (1–3 years) — requires hiring, depends on budget constraints. | D8: 4.5% of 29.5%
A9: 5 | B9: Scoring Logic | C9: THE normalizes the raw ratio using z-scoring across all ranked universities. Lower ratio = higher z-score = better rank position. Institutions with ratio <10:1 typically score in the top quartile. Ratios >25:1 fall in the bottom quartile. PPP adjustment is NOT applied to this ratio (it's a headcount metric, not financial). | D9: Normalization
A11: Improvement Strategies (from Strategic Roadmap)
A12: • Hire high-quality faculty strategically to reduce ratio in key departments.
A13: • Reduce large class sizes using teaching assistants and lab demonstrators.
A14: • Start recruitment to improve ratio in departments with highest student load.
A15: • Recruit 2–5 international faculty / postdocs with teaching responsibilities.
A16: • Strategic hiring plan aligned with budget constraints and growth targets.
A17: • Difficulty: 🟡 Moderate (1–3 years). Requires hiring; depends on budget constraints.
A18: • Quick wins: deploy TAs/tutors/adjuncts in high-load departments while permanent hiring progresses.

Sheet 1. Academic Staff FTE
A1: Academic Staff — Full-Time Equivalent (FTE) by Category
A2: THE-compliant FTE: professors, assoc. professors, asst. professors, lecturers, research fellows with teaching | Excludes admin/support
A3: S.No. | B3: University Name | C3: Country | D3: Professors (FTE) | E3: Associate Professors (FTE) | F3: Assistant Professors (FTE) | G3: Lecturers / Instructors (FTE) | H3: Research Fellows with Teaching (FTE) | I3: Other Teaching Staff (FTE) | J3: Total Academic Staff FTE | K3: Reporting Year
A4: 1 | J4: =SUM(D4:I4) -> 0
A5: 2 | J5: =SUM(D5:I5) -> 0
A6: 3 | J6: =SUM(D6:I6) -> 0
A7: 4 | J7: =SUM(D7:I7) -> 0
A8: 5 | J8: =SUM(D8:I8) -> 0
A9: 6 | J9: =SUM(D9:I9) -> 0
A10: 7 | J10: =SUM(D10:I10) -> 0
A11: 8 | J11: =SUM(D11:I11) -> 0
A12: 9 | J12: =SUM(D12:I12) -> 0
A13: 10 | J13: =SUM(D13:I13) -> 0
A14: 11 | J14: =SUM(D14:I14) -> 0
A15: 12 | J15: =SUM(D15:I15) -> 0
... A33: 30 | J33: =SUM(D33:I33) -> 0
A35: Department-Level Staff FTE Breakdown (Per University)
A36: S.No. | B36: Department / School Name | C36: Faculty / College | D36: Professors | E36: Assoc. Prof | F36: Asst. Prof | G36: Lecturers | H36: Research Fellows (Teaching) | I36: Other Teaching | J36: Total FTE | K36: University Name
A37: 1 | J37: =SUM(D37:I37) -> 0
A38: 2 | J38: =SUM(D38:I38) -> 0
A39: 3 | J39: =SUM(D39:I39) -> 0
A40: 4 | J40: =SUM(D40:I40) -> 0
A41: 5 | J41: =SUM(D41:I41) -> 0
A42: 6 | J42: =SUM(D42:I42) -> 0
A43: 7 | J43: =SUM(D43:I43) -> 0
A44: 8 | J44: =SUM(D44:I44) -> 0
A45: 9 | J45: =SUM(D45:I45) -> 0
A46: 10 | J46: =SUM(D46:I46) -> 0
A47: 11 | J47: =SUM(D47:I47) -> 0
A48: 12 | J48: =SUM(D48:I48) -> 0
... A76: 40 | J76: =SUM(D76:I76) -> 0

Sheet 2. Student FTE
A1: Student Enrolment — Full-Time Equivalent (FTE) by Level
A2: All enrolled students: UG + PG (taught) + PG (research/PhD) + Professional | Part-time at pro-rata FTE
A3: S.No. | B3: University Name | C3: Country | D3: UG Full-Time | E3: UG Part-Time (FTE equiv.) | F3: PG Taught Full-Time | G3: PG Taught Part-Time (FTE) | H3: PG Research/PhD Full-Time | I3: PG Research/PhD Part-Time (FTE) | J3: Total Student FTE | K3: Reporting Year
A4: 1 | J4: =SUM(D4:I4) -> 0
A5: 2 | J5: =SUM(D5:I5) -> 0
A6: 3 | J6: =SUM(D6:I6) -> 0
A7: 4 | J7: =SUM(D7:I7) -> 0
A8: 5 | J8: =SUM(D8:I8) -> 0
A9: 6 | J9: =SUM(D9:I9) -> 0
A10: 7 | J10: =SUM(D10:I10) -> 0
A11: 8 | J11: =SUM(D11:I11) -> 0
A12: 9 | J12: =SUM(D12:I12) -> 0
A13: 10 | J13: =SUM(D13:I13) -> 0
A14: 11 | J14: =SUM(D14:I14) -> 0
A15: 12 | J15: =SUM(D15:I15) -> 0
... A33: 30 | J33: =SUM(D33:I33) -> 0
A35: Department-Level Student FTE Breakdown (Per University)
A36: S.No. | B36: Department / School Name | C36: Faculty / College | D36: UG FT | E36: UG PT (FTE) | F36: PG Taught FT | G36: PG Taught PT (FTE) | H36: PhD FT | I36: PhD PT (FTE) | J36: Total Student FTE | K36: University Name
A37: 1 | J37: =SUM(D37:I37) -> 0
A38: 2 | J38: =SUM(D38:I38) -> 0
A39: 3 | J39: =SUM(D39:I39) -> 0
A40: 4 | J40: =SUM(D40:I40) -> 0
A41: 5 | J41: =SUM(D41:I41) -> 0
A42: 6 | J42: =SUM(D42:I42) -> 0
A43: 7 | J43: =SUM(D43:I43) -> 0
A44: 8 | J44: =SUM(D44:I44) -> 0
A45: 9 | J45: =SUM(D45:I45) -> 0
A46: 10 | J46: =SUM(D46:I46) -> 0
A47: 11 | J47: =SUM(D47:I47) -> 0
A48: 12 | J48: =SUM(D48:I48) -> 0
... A76: 40 | J76: =SUM(D76:I76) -> 0

Sheet 3. Ratio Calculation
A1: Staff-to-Student Ratio — Calculation & Scoring
A2: Ratio = Academic Staff FTE ÷ Student FTE | Lower ratio = better | Z-scored across all universities
A3: S.No. | B3: University Name | C3: Country | D3: Academic Staff FTE | E3: Student FTE | F3: Staff-to-Student Ratio (1:X) | G3: Students per Staff | H3: Z-Score | I3: Normalized Score (0–100) | J3: Reporting Year
A4: 1 | D4: ='1. Academic Staff FTE'!J4 -> 0 | E4: ='2. Student FTE'!J4 -> 0 | F4: =IF(D4>0,1/ROUND(E4/D4,1),0) -> 0 | G4: =IF(D4>0,E4/D4,0) -> 0 | H4: =IFERROR(-1*(G4-AVERAGE($G$4:$G$33))/STDEV($G$4:$G$33),0) -> 0 | I4: =IFERROR(IF(MAX($H$4:$H$33)-MIN($H$4:$H$33)>0,(H4-MIN($H$4:$H$33))/(MAX($H$4:$H$33)-MIN($H$4:$H$33))*100,0),0) -> 0
A5: 2 | D5: ='1. Academic Staff FTE'!J5 -> 0 | E5: ='2. Student FTE'!J5 -> 0 | F5: =IF(D5>0,1/ROUND(E5/D5,1),0) -> 0 | G5: =IF(D5>0,E5/D5,0) -> 0 | H5: =IFERROR(-1*(G5-AVERAGE($G$4:$G$33))/STDEV($G$4:$G$33),0) -> 0 | I5: =IFERROR(IF(MAX($H$4:$H$33)-MIN($H$4:$H$33)>0,(H5-MIN($H$4:$H$33))/(MAX($H$4:$H$33)-MIN($H$4:$H$33))*100,0),0) -> 0
A6: 3 | D6: ='1. Academic Staff FTE'!J6 -> 0 | E6: ='2. Student FTE'!J6 -> 0 | F6: =IF(D6>0,1/ROUND(E6/D6,1),0) -> 0 | G6: =IF(D6>0,E6/D6,0) -> 0 | H6: =IFERROR(-1*(G6-AVERAGE($G$4:$G$33))/STDEV($G$4:$G$33),0) -> 0 | I6: =IFERROR(IF(MAX($H$4:$H$33)-MIN($H$4:$H$33)>0,(H6-MIN($H$4:$H$33))/(MAX($H$4:$H$33)-MIN($H$4:$H$33))*100,0),0) -> 0
A7: 4 | D7: ='1. Academic Staff FTE'!J7 -> 0 | E7: ='2. Student FTE'!J7 -> 0 | F7: =IF(D7>0,1/ROUND(E7/D7,1),0) -> 0 | G7: =IF(D7>0,E7/D7,0) -> 0 | H7: =IFERROR(-1*(G7-AVERAGE($G$4:$G$33))/STDEV($G$4:$G$33),0) -> 0 | I7: =IFERROR(IF(MAX($H$4:$H$33)-MIN($H$4:$H$33)>0,(H7-MIN($H$4:$H$33))/(MAX($H$4:$H$33)-MIN($H$4:$H$33))*100,0),0) -> 0
A8: 5 | D8: ='1. Academic Staff FTE'!J8 -> 0 | E8: ='2. Student FTE'!J8 -> 0 | F8: =IF(D8>0,1/ROUND(E8/D8,1),0) -> 0 | G8: =IF(D8>0,E8/D8,0) -> 0 | H8: =IFERROR(-1*(G8-AVERAGE($G$4:$G$33))/STDEV($G$4:$G$33),0) -> 0 | I8: =IFERROR(IF(MAX($H$4:$H$33)-MIN($H$4:$H$33)>0,(H8-MIN($H$4:$H$33))/(MAX($H$4:$H$33)-MIN($H$4:$H$33))*100,0),0) -> 0
A9: 6 | D9: ='1. Academic Staff FTE'!J9 -> 0 | E9: ='2. Student FTE'!J9 -> 0 | F9: =IF(D9>0,1/ROUND(E9/D9,1),0) -> 0 | G9: =IF(D9>0,E9/D9,0) -> 0 | H9: =IFERROR(-1*(G9-AVERAGE($G$4:$G$33))/STDEV($G$4:$G$33),0) -> 0 | I9: =IFERROR(IF(MAX($H$4:$H$33)-MIN($H$4:$H$33)>0,(H9-MIN($H$4:$H$33))/(MAX($H$4:$H$33)-MIN($H$4:$H$33))*100,0),0) -> 0
A10: 7 | D10: ='1. Academic Staff FTE'!J10 -> 0 | E10: ='2. Student FTE'!J10 -> 0 | F10: =IF(D10>0,1/ROUND(E10/D10,1),0) -> 0 | G10: =IF(D10>0,E10/D10,0) -> 0 | H10: =IFERROR(-1*(G10-AVERAGE($G$4:$G$33))/STDEV($G$4:$G$33),0) -> 0 | I10: =IFERROR(IF(MAX($H$4:$H$33)-MIN($H$4:$H$33)>0,(H10-MIN($H$4:$H$33))/(MAX($H$4:$H$33)-MIN($H$4:$H$33))*100,0),0) -> 0
A11: 8 | D11: ='1. Academic Staff FTE'!J11 -> 0 | E11: ='2. Student FTE'!J11 -> 0 | F11: =IF(D11>0,1/ROUND(E11/D11,1),0) -> 0 | G11: =IF(D11>0,E11/D11,0) -> 0 | H11: =IFERROR(-1*(G11-AVERAGE($G$4:$G$33))/STDEV($G$4:$G$33),0) -> 0 | I11: =IFERROR(IF(MAX($H$4:$H$33)-MIN($H$4:$H$33)>0,(H11-MIN($H$4:$H$33))/(MAX($H$4:$H$33)-MIN($H$4:$H$33))*100,0),0) -> 0
A12: 9 | D12: ='1. Academic Staff FTE'!J12 -> 0 | E12: ='2. Student FTE'!J12 -> 0 | F12: =IF(D12>0,1/ROUND(E12/D12,1),0) -> 0 | G12: =IF(D12>0,E12/D12,0) -> 0 | H12: =IFERROR(-1*(G12-AVERAGE($G$4:$G$33))/STDEV($G$4:$G$33),0) -> 0 | I12: =IFERROR(IF(MAX($H$4:$H$33)-MIN($H$4:$H$33)>0,(H12-MIN($H$4:$H$33))/(MAX($H$4:$H$33)-MIN($H$4:$H$33))*100,0),0) -> 0
A13: 10 | D13: ='1. Academic Staff FTE'!J13 -> 0 | E13: ='2. Student FTE'!J13 -> 0 | F13: =IF(D13>0,1/ROUND(E13/D13,1),0) -> 0 | G13: =IF(D13>0,E13/D13,0) -> 0 | H13: =IFERROR(-1*(G13-AVERAGE($G$4:$G$33))/STDEV($G$4:$G$33),0) -> 0 | I13: =IFERROR(IF(MAX($H$4:$H$33)-MIN($H$4:$H$33)>0,(H13-MIN($H$4:$H$33))/(MAX($H$4:$H$33)-MIN($H$4:$H$33))*100,0),0) -> 0
A14: 11 | D14: ='1. Academic Staff FTE'!J14 -> 0 | E14: ='2. Student FTE'!J14 -> 0 | F14: =IF(D14>0,1/ROUND(E14/D14,1),0) -> 0 | G14: =IF(D14>0,E14/D14,0) -> 0 | H14: =IFERROR(-1*(G14-AVERAGE($G$4:$G$33))/STDEV($G$4:$G$33),0) -> 0 | I14: =IFERROR(IF(MAX($H$4:$H$33)-MIN($H$4:$H$33)>0,(H14-MIN($H$4:$H$33))/(MAX($H$4:$H$33)-MIN($H$4:$H$33))*100,0),0) -> 0
A15: 12 | D15: ='1. Academic Staff FTE'!J15 -> 0 | E15: ='2. Student FTE'!J15 -> 0 | F15: =IF(D15>0,1/ROUND(E15/D15,1),0) -> 0 | G15: =IF(D15>0,E15/D15,0) -> 0 | H15: =IFERROR(-1*(G15-AVERAGE($G$4:$G$33))/STDEV($G$4:$G$33),0) -> 0 | I15: =IFERROR(IF(MAX($H$4:$H$33)-MIN($H$4:$H$33)>0,(H15-MIN($H$4:$H$33))/(MAX($H$4:$H$33)-MIN($H$4:$H$33))*100,0),0) -> 0
... A33: 30 | D33: ='1. Academic Staff FTE'!J33 -> 0 | E33: ='2. Student FTE'!J33 -> 0 | F33: =IF(D33>0,1/ROUND(E33/D33,1),0) -> 0 | G33: =IF(D33>0,E33/D33,0) -> 0 | H33: =IFERROR(-1*(G33-AVERAGE($G$4:$G$33))/STDEV($G$4:$G$33),0) -> 0 | I33: =IFERROR(IF(MAX($H$4:$H$33)-MIN($H$4:$H$33)>0,(H33-MIN($H$4:$H$33))/(MAX($H$4:$H$33)-MIN($H$4:$H$33))*100,0),0) -> 0
A35: Summary Statistics
A36: Average Students per Staff | F36: =IF(COUNTA(G4:G33)>0,AVERAGE(G4:G33),0) -> 0
A37: Best (Lowest) Ratio | F37: =MIN(G4:G33) -> 0
A38: Worst (Highest) Ratio | F38: =MAX(G4:G33) -> 0
A39: Median Ratio | F39: =MEDIAN(G4:G33) -> 0
A40: Std Deviation | F40: =IF(COUNTA(G4:G33)>1,STDEV(G4:G33),0) -> 0

Sheet 4. Dept-Level Ratios
A1: Department-Level Staff-to-Student Ratios — Identifying Hotspots
A2: Granular view showing which departments have the worst ratios | Prioritize hiring where needed most
A3: S.No. | B3: Department / School | C3: Faculty / College | D3: Staff FTE | E3: Student FTE | F3: Students per Staff | G3: Target Ratio | H3: Gap to Target | I3: Priority (High/Med/Low)
A4: 1 | F4: =IF(D4>0,E4/D4,0) -> 0 | H4: =IF(AND(F4>0,G4>0),F4-G4,0) -> 0 | I4: =IF(H4>10,"High",IF(H4>5,"Medium",IF(H4>0,"Low","On Target"))) -> On Target
A5: 2 | F5: =IF(D5>0,E5/D5,0) -> 0 | H5: =IF(AND(F5>0,G5>0),F5-G5,0) -> 0 | I5: =IF(H5>10,"High",IF(H5>5,"Medium",IF(H5>0,"Low","On Target"))) -> On Target
A6: 3 | F6: =IF(D6>0,E6/D6,0) -> 0 | H6: =IF(AND(F6>0,G6>0),F6-G6,0) -> 0 | I6: =IF(H6>10,"High",IF(H6>5,"Medium",IF(H6>0,"Low","On Target"))) -> On Target
A7: 4 | F7: =IF(D7>0,E7/D7,0) -> 0 | H7: =IF(AND(F7>0,G7>0),F7-G7,0) -> 0 | I7: =IF(H7>10,"High",IF(H7>5,"Medium",IF(H7>0,"Low","On Target"))) -> On Target
A8: 5 | F8: =IF(D8>0,E8/D8,0) -> 0 | H8: =IF(AND(F8>0,G8>0),F8-G8,0) -> 0 | I8: =IF(H8>10,"High",IF(H8>5,"Medium",IF(H8>0,"Low","On Target"))) -> On Target
A9: 6 | F9: =IF(D9>0,E9/D9,0) -> 0 | H9: =IF(AND(F9>0,G9>0),F9-G9,0) -> 0 | I9: =IF(H9>10,"High",IF(H9>5,"Medium",IF(H9>0,"Low","On Target"))) -> On Target
A10: 7 | F10: =IF(D10>0,E10/D10,0) -> 0 | H10: =IF(AND(F10>0,G10>0),F10-G10,0) -> 0 | I10: =IF(H10>10,"High",IF(H10>5,"Medium",IF(H10>0,"Low","On Target"))) -> On Target
A11: 8 | F11: =IF(D11>0,E11/D11,0) -> 0 | H11: =IF(AND(F11>0,G11>0),F11-G11,0) -> 0 | I11: =IF(H11>10,"High",IF(H11>5,"Medium",IF(H11>0,"Low","On Target"))) -> On Target
A12: 9 | F12: =IF(D12>0,E12/D12,0) -> 0 | H12: =IF(AND(F12>0,G12>0),F12-G12,0) -> 0 | I12: =IF(H12>10,"High",IF(H12>5,"Medium",IF(H12>0,"Low","On Target"))) -> On Target
A13: 10 | F13: =IF(D13>0,E13/D13,0) -> 0 | H13: =IF(AND(F13>0,G13>0),F13-G13,0) -> 0 | I13: =IF(H13>10,"High",IF(H13>5,"Medium",IF(H13>0,"Low","On Target"))) -> On Target
A14: 11 | F14: =IF(D14>0,E14/D14,0) -> 0 | H14: =IF(AND(F14>0,G14>0),F14-G14,0) -> 0 | I14: =IF(H14>10,"High",IF(H14>5,"Medium",IF(H14>0,"Low","On Target"))) -> On Target
A15: 12 | F15: =IF(D15>0,E15/D15,0) -> 0 | H15: =IF(AND(F15>0,G15>0),F15-G15,0) -> 0 | I15: =IF(H15>10,"High",IF(H15>5,"Medium",IF(H15>0,"Low","On Target"))) -> On Target
... A43: 40 | F43: =IF(D43>0,E43/D43,0) -> 0 | H43: =IF(AND(F43>0,G43>0),F43-G43,0) -> 0 | I43: =IF(H43>10,"High",IF(H43>5,"Medium",IF(H43>0,"Low","On Target"))) -> On Target

Sheet 5. YoY Trend
A1: Staff-to-Student Ratio — 5-Year Trend Analysis
A2: Track ratio improvement over 5 years | Demonstrates investment in teaching environment
A3: S.No. | B3: University Name | C3: Country | D3: Year 1 Ratio | E3: Year 2 Ratio | F3: Year 3 Ratio | G3: Year 4 Ratio | H3: Year 5 Ratio (Current) | I3: 5-Year Change | J3: Improvement Rate (%) | K3: Trend
A4: 1 | I4: =IF(AND(D4>0,H4>0),D4-H4,0) -> 0 | J4: =IFERROR(IF(D4>0,(D4-H4)/D4*100,0),0) -> 0 | K4: =IF(I4>2,"Improving",IF(I4>0,"Stable",IF(I4<-2,"Worsening","Flat"))) -> Flat
A5: 2 | I5: =IF(AND(D5>0,H5>0),D5-H5,0) -> 0 | J5: =IFERROR(IF(D5>0,(D5-H5)/D5*100,0),0) -> 0 | K5: =IF(I5>2,"Improving",IF(I5>0,"Stable",IF(I5<-2,"Worsening","Flat"))) -> Flat
A6: 3 | I6: =IF(AND(D6>0,H6>0),D6-H6,0) -> 0 | J6: =IFERROR(IF(D6>0,(D6-H6)/D6*100,0),0) -> 0 | K6: =IF(I6>2,"Improving",IF(I6>0,"Stable",IF(I6<-2,"Worsening","Flat"))) -> Flat
A7: 4 | I7: =IF(AND(D7>0,H7>0),D7-H7,0) -> 0 | J7: =IFERROR(IF(D7>0,(D7-H7)/D7*100,0),0) -> 0 | K7: =IF(I7>2,"Improving",IF(I7>0,"Stable",IF(I7<-2,"Worsening","Flat"))) -> Flat
A8: 5 | I8: =IF(AND(D8>0,H8>0),D8-H8,0) -> 0 | J8: =IFERROR(IF(D8>0,(D8-H8)/D8*100,0),0) -> 0 | K8: =IF(I8>2,"Improving",IF(I8>0,"Stable",IF(I8<-2,"Worsening","Flat"))) -> Flat
A9: 6 | I9: =IF(AND(D9>0,H9>0),D9-H9,0) -> 0 | J9: =IFERROR(IF(D9>0,(D9-H9)/D9*100,0),0) -> 0 | K9: =IF(I9>2,"Improving",IF(I9>0,"Stable",IF(I9<-2,"Worsening","Flat"))) -> Flat
A10: 7 | I10: =IF(AND(D10>0,H10>0),D10-H10,0) -> 0 | J10: =IFERROR(IF(D10>0,(D10-H10)/D10*100,0),0) -> 0 | K10: =IF(I10>2,"Improving",IF(I10>0,"Stable",IF(I10<-2,"Worsening","Flat"))) -> Flat
A11: 8 | I11: =IF(AND(D11>0,H11>0),D11-H11,0) -> 0 | J11: =IFERROR(IF(D11>0,(D11-H11)/D11*100,0),0) -> 0 | K11: =IF(I11>2,"Improving",IF(I11>0,"Stable",IF(I11<-2,"Worsening","Flat"))) -> Flat
A12: 9 | I12: =IF(AND(D12>0,H12>0),D12-H12,0) -> 0 | J12: =IFERROR(IF(D12>0,(D12-H12)/D12*100,0),0) -> 0 | K12: =IF(I12>2,"Improving",IF(I12>0,"Stable",IF(I12<-2,"Worsening","Flat"))) -> Flat
A13: 10 | I13: =IF(AND(D13>0,H13>0),D13-H13,0) -> 0 | J13: =IFERROR(IF(D13>0,(D13-H13)/D13*100,0),0) -> 0 | K13: =IF(I13>2,"Improving",IF(I13>0,"Stable",IF(I13<-2,"Worsening","Flat"))) -> Flat
A14: 11 | I14: =IF(AND(D14>0,H14>0),D14-H14,0) -> 0 | J14: =IFERROR(IF(D14>0,(D14-H14)/D14*100,0),0) -> 0 | K14: =IF(I14>2,"Improving",IF(I14>0,"Stable",IF(I14<-2,"Worsening","Flat"))) -> Flat
A15: 12 | I15: =IF(AND(D15>0,H15>0),D15-H15,0) -> 0 | J15: =IFERROR(IF(D15>0,(D15-H15)/D15*100,0),0) -> 0 | K15: =IF(I15>2,"Improving",IF(I15>0,"Stable",IF(I15<-2,"Worsening","Flat"))) -> Flat
... A33: 30 | I33: =IF(AND(D33>0,H33>0),D33-H33,0) -> 0 | J33: =IFERROR(IF(D33>0,(D33-H33)/D33*100,0),0) -> 0 | K33: =IF(I33>2,"Improving",IF(I33>0,"Stable",IF(I33<-2,"Worsening","Flat"))) -> Flat

Sheet 6. Hiring & TA Plan
A1: Strategic Hiring & Teaching Assistant Deployment Plan
A2: Targeted actions to reduce students-per-staff in priority departments | Short-term TAs + long-term hiring
A3: S.No. | B3: Department / School | C3: Current Students/Staff | D3: Target Ratio | E3: Additional Staff Needed | F3: TAs / Tutors to Deploy (Interim) | G3: Budget Required (INR L / USD K) | H3: Timeline | I3: Status (Done/IP/Planned)
A4: 1 | E4: =IF(AND(C4>0,D4>0),CEILING((C4-D4)/D4*10,1),0) -> 0
A5: 2 | E5: =IF(AND(C5>0,D5>0),CEILING((C5-D5)/D5*10,1),0) -> 0
A6: 3 | E6: =IF(AND(C6>0,D6>0),CEILING((C6-D6)/D6*10,1),0) -> 0
A7: 4 | E7: =IF(AND(C7>0,D7>0),CEILING((C7-D7)/D7*10,1),0) -> 0
A8: 5 | E8: =IF(AND(C8>0,D8>0),CEILING((C8-D8)/D8*10,1),0) -> 0
A9: 6 | E9: =IF(AND(C9>0,D9>0),CEILING((C9-D9)/D9*10,1),0) -> 0
A10: 7 | E10: =IF(AND(C10>0,D10>0),CEILING((C10-D10)/D10*10,1),0) -> 0
A11: 8 | E11: =IF(AND(C11>0,D11>0),CEILING((C11-D11)/D11*10,1),0) -> 0
A12: 9 | E12: =IF(AND(C12>0,D12>0),CEILING((C12-D12)/D12*10,1),0) -> 0
A13: 10 | E13: =IF(AND(C13>0,D13>0),CEILING((C13-D13)/D13*10,1),0) -> 0
A14: 11 | E14: =IF(AND(C14>0,D14>0),CEILING((C14-D14)/D14*10,1),0) -> 0
A15: 12 | E15: =IF(AND(C15>0,D15>0),CEILING((C15-D15)/D15*10,1),0) -> 0
... A33: 30 | E33: =IF(AND(C33>0,D33>0),CEILING((C33-D33)/D33*10,1),0) -> 0

Sheet 7. FTE Rules & Exclusions
A1: FTE Counting Rules — Inclusions & Exclusions per THE Definition
A2: Precise definitions to ensure THE-compliant FTE counts for both staff and students
A3: # | B3: Category | C3: Rule / Definition | D3: Include / Exclude | E3: Notes
A4: 1 | B4: Staff | C4: Full-time professor/associate/assistant | D4: Include | E4: Core academic staff
A5: 2 | B5: Staff | C5: Part-time professor (e.g., 50% appointment) | D5: Include | E5: Pro-rata
A6: 3 | B6: Staff | C6: Lecturer / instructor with teaching duties | D6: Include | E6: Teaching-focused staff
A7: 4 | B7: Staff | C7: Research fellow WITH teaching responsibilities | D7: Include | E7: Must have formal teaching load
A8: 5 | B8: Staff | C8: Research-only staff (no teaching) | D8: Exclude | E8: Not part of teaching environment
A9: 6 | B9: Staff | C9: Administrative staff (registrar, accounts, etc.) | D9: Exclude | E9: Non-academic
A10: 7 | B10: Staff | C10: Technical / lab support staff | D10: Exclude | E10: Support role
A11: 8 | B11: Staff | C11: Visiting faculty (<0.5 FTE or <1 semester) | D11: Exclude | E11: Below threshold
A12: 9 | B12: Staff | C12: Visiting faculty (≥0.5 FTE and ≥1 semester) | D12: Include | E12: Meets threshold
A13: 10 | B13: Staff | C13: Emeritus professor (no active teaching) | D13: Exclude | E13: Inactive
A14: 11 | B14: Staff | C14: Teaching assistants / tutors (not faculty) | D14: Exclude | E14: Not academic staff per THE
A15: 12 | B15: Staff | C15: Adjunct faculty (<0.25 FTE) | D15: Exclude | E15: Below threshold
... A24: 21 | B24: Student | C24: Non-degree certificate / audit student | D24: Exclude | E24: Not enrolled in degree programme

Sheet 8. Benchmarking
A1: Benchmarking — Staff-to-Student Ratio
A2: Compare against peers, aspirational targets, and global top performers
A3: S.No. | B3: University / Benchmark | C3: Staff FTE | D3: Student FTE | E3: Students/Staff | F3: Score (0–100) | G3: Peer Group
A4: 1 | B4: Your Institution | G4: Target
A5: 2 | B5: Global Top 10 Average | G5: Aspirational
A6: 3 | B6: National Average | G6: National
A7: 4 | B7: Peer Group Average | G7: Peer
A8: 5 | B8: THE Top Quartile Benchmark | G8: <10:1
A9: 1
A10: 2
A11: 3
A12: 4
A13: 5
A14: 6
A15: 7
A16: 8
A17: 9
A18: 10
A19: 11
A20: 12
... A23: 15

Sheet 9. Risk Assessment
A1: Staff-to-Student Ratio — Risk Assessment & Mitigation
A2: Risks specific to improving the staff-to-student ratio | From THE Risk Matrix
A3: # | B3: Risk | C3: Level | D3: Impact on Ratio | E3: Mitigation | F3: Owner
A4: 1 | B4: Faculty shortages / hiring freezes | C4: 🟡 Medium | D4: Cannot reduce ratio; remains high vs peers | E4: Strategic hiring plan; prioritize high-load departments; adjunct/TA bridge
A5: 2 | B5: Budget constraints limiting new hires | C5: 🟡 Medium | D5: Cannot afford to recruit additional staff | E5: External grants, CSR funding, government support, phased hiring
A6: 3 | B6: Rapid student enrolment growth | C6: 🟡 Medium | D6: Student FTE grows faster than staff FTE; ratio worsens | E6: Cap enrolment growth; hire proportionally; use TA deployment
A7: 4 | B7: Misclassification of staff (inflating FTE) | C7: 🔴 High | D7: Audit reveals non-compliant staff counted; ratio corrected upward | E7: Strict adherence to THE FTE definitions; internal audit
A8: 5 | B8: Counting non-teaching research staff | C8: 🔴 High | D8: Research-only staff cannot be counted; inflates numerator | E8: Separate teaching vs research-only in HR database
A9: 6 | B9: Part-time staff FTE miscalculation | C9: 🟡 Medium | D9: Overestimating part-time FTE gives false low ratio | E9: Standardize FTE calculation: contractual hours ÷ full-time hours
A10: 7 | B10: Distance/online student miscounting | C10: 🟡 Medium | D10: Including excluded categories inflates denominator | E10: Verify THE guidelines on distance learners per cycle
A11: 8 | B11: Data submission errors to THE | C11: 🔴 High | D11: Incorrect ratio submitted; affects ranking directly | E11: Double-check all figures; internal + external peer review before submission

Sheet 10. Data Quality Audit
A1: Staff-to-Student Ratio — Data Quality & Audit Checklist
A2: Validation checks for SSR data (4.5% of total WUR score)
A3: # | B3: Quality Check | C3: Description | D3: Status (✓/✗/IP) | E3: Date | F3: Reviewer
A4: 1 | B4: Academic staff FTE definition compliance | C4: FTE counts follow THE definition: professors, assoc/asst professors, lecturers, research fellows WITH teaching duties only
A5: 2 | B5: Research-only staff excluded | C5: Staff with no formal teaching load excluded from academic staff FTE count
A6: 3 | B6: Admin/technical staff excluded | C6: Administrative, technical, and support staff not counted in academic FTE
A7: 4 | B7: Visiting faculty threshold | C7: Visiting faculty counted only if ≥0.5 FTE and ≥1 semester appointment
A8: 5 | B8: Part-time staff FTE calculation | C8: Part-time staff FTE = contractual hours ÷ full-time equivalent hours; method documented
A9: 6 | B9: Student FTE definition compliance | C9: All enrolled degree-seeking students counted: UG + PG taught + PG research/PhD
A10: 7 | B10: Part-time student FTE calculation | C10: Part-time students at proportional FTE; method documented and consistently applied
A11: 8 | B11: Distance learner treatment | C11: Distance/online-only students included or excluded per current THE cycle guidelines
A12: 9 | B12: Exchange student exclusion | C12: Short-term, non-degree exchange students (<1 semester) excluded from count
A13: 10 | B13: Non-degree student exclusion | C13: Certificate, audit, and non-degree students excluded from FTE count
A14: 11 | B14: HR records cross-reference | C14: Staff FTE verified against official HR/establishment records (payroll, appointment letters)
A15: 12 | B15: Registrar records cross-reference | C15: Student FTE verified against official registrar enrollment records
... A23: 20 | B23: Reproducibility test | C23: Ratio independently reproducible from source HR + registrar records within ±2%
