Workbook

Sheet Methodology Overview
A1: THE WUR — Research Environment (29%) → Research Income PPP-Adjusted (5.5%)
A2: Measures Competitiveness in Securing Research Funding | PPP-Adjusted per Staff FTE | 5.5% of WUR
A4: # | B4: Component | C4: Description & Methodology | D4: Weight
A5: 1 | B5: Research Income (PPP-Adjusted) | C5: Total externally-sourced research income normalized by academic staff FTE and adjusted for Purchasing Power Parity. Unlike Institutional Income (2.5% in Teaching pillar) which includes ALL revenue, this indicator counts ONLY research-related income — grants, contracts, and sponsored projects. Signals the institution's ability to compete for and win research funding from external sources. | D5: 5.5% of WUR
A6: 2 | B6: Research Income (Numerator) | C6: ONLY externally-sourced research funding: competitive government grants (DST, SERB, DBT, ICMR, CSIR, NSF, ERC, etc.), industry-sponsored R&D contracts, international research collaborations, foundation/philanthropy grants for research, and commissioned research. EXCLUDES: internal university allocations, tuition fees, block grants not earmarked for research, endowment income, consultancy revenue, and institutional overheads. | D6: Numerator
A7: 3 | B7: Academic Staff FTE (Denominator) | C7: Same THE-compliant FTE definition used across all pillars. Professors, associate/assistant professors, lecturers, research fellows with teaching. Excludes admin, technical, support, research-only staff. MUST match the same FTE used in Teaching sub-indicators (SSR, Doctorates/Staff, Income). | D7: Denominator
A8: 4 | B8: PPP Adjustment | C8: World Bank PPP conversion factors applied to convert local-currency research income to internationally comparable PPP-adjusted USD. Essential for fair comparison: ₹1 crore in India buys more research capacity than $130K in the USA. | D8: Normalization
A9: 5 | B9: Scoring Logic | C9: (Research Income PPP-USD) ÷ Academic Staff FTE → z-scored across all ranked universities. Higher income per staff = higher score. This metric rewards competitive grant-winning capability, not just institutional wealth. | D9: Z-scoring
A10: 6 | B10: Context: Research Environment | C10: Research Environment (29%) = Research Reputation (18%) + Research Income PPP (5.5%) + Research Productivity (5.5%). Research income at 5.5% is directly controllable through active grant-seeking. Difficulty: 🟡 Moderate (1–3 years) — depends on grant pipeline development. | D10: 5.5% of 29%
A12: Key Difference: Research Income (5.5%) vs Institutional Income (2.5%)
A13: # | B13: Feature | C13: Research Income (5.5% — Research Env.) | D13: Institutional Income (2.5% — Teaching)
A14: 1 | B14: Scope | C14: ONLY externally-sourced research funding | D14: ALL institutional revenue (fees, grants, endowment, etc.)
A15: 2 | B15: Pillar | C15: Research Environment (29%) | D15: Teaching (29.5%)
A16: 3 | B16: Signal | C16: Competitive research grant-winning ability | D16: Overall financial health / investment capacity
A17: 4 | B17: Excludes | C17: Tuition, block grants, consultancy, internal allocation | D17: Capital grants, asset sales, endowment principal
A18: 5 | B18: Includes | C18: Govt grants, industry R&D, intl collab, foundation grants | D18: Govt grants, tuition, industry, endowment, philanthropy, all ops
A19: 6 | B19: PPP-Adjusted | C19: Yes | D19: Yes
A20: 7 | B20: Normalized by | C20: Academic Staff FTE | D20: Academic Staff FTE
A22: Improvement Strategies
A23: • Train faculty on competitive grant proposal writing (DST, SERB, DBT, ERC, NSF).
A24: • Establish a Grant Support Office providing pre-award and post-award support.
A25: • Build industry-sponsored R&D partnerships and co-funded projects.
A26: • Pursue international research collaborations with funded project components.
A27: • Target foundation grants (Wellcome Trust, BMGF, Ford Foundation) for specific research areas.
A28: • Difficulty: 🟡 Moderate (1–3 years). Active grant-seeking yields results within 1–2 grant cycles.

Sheet 1. Research Income
A1: Research Income — Externally-Sourced Funding by Category (Most Recent Year)
A2: ONLY external research funding | Govt grants + industry R&D + intl collab + foundation grants | NOT tuition/consultancy
A3: S.No. | B3: University Name | C3: Country | D3: Govt Competitive Grants (DST/SERB/DBT/ICMR/CSIR etc.) | E3: Industry-Sponsored R&D Contracts | F3: International Research Collaborations | G3: Foundation / Philanthropy Research Grants | H3: Commissioned / Contract Research (Other) | I3: Total Research Income (Local Currency) | J3: Reporting Year
A4: 1 | I4: =SUM(D4:H4) -> 0
A5: 2 | I5: =SUM(D5:H5) -> 0
A6: 3 | I6: =SUM(D6:H6) -> 0
A7: 4 | I7: =SUM(D7:H7) -> 0
A8: 5 | I8: =SUM(D8:H8) -> 0
A9: 6 | I9: =SUM(D9:H9) -> 0
A10: 7 | I10: =SUM(D10:H10) -> 0
A11: 8 | I11: =SUM(D11:H11) -> 0
A12: 9 | I12: =SUM(D12:H12) -> 0
A13: 10 | I13: =SUM(D13:H13) -> 0
A14: 11 | I14: =SUM(D14:H14) -> 0
A15: 12 | I15: =SUM(D15:H15) -> 0
... A33: 30 | I33: =SUM(D33:H33) -> 0
A35: 5-Year Research Income History
A36: S.No. | B36: University Name | C36: Country | D36: Year 1 (Local Currency) | E36: Year 2 | F36: Year 3 | G36: Year 4 | H36: Year 5 (Current) | I36: 5-Year Total | J36: CAGR (%)
A37: 1 | I37: =SUM(D37:H37) -> 0 | J37: =IFERROR(IF(AND(D37>0,H37>0),(H37/D37)^(1/4)-1,0)*100,0) -> 0
A38: 2 | I38: =SUM(D38:H38) -> 0 | J38: =IFERROR(IF(AND(D38>0,H38>0),(H38/D38)^(1/4)-1,0)*100,0) -> 0
A39: 3 | I39: =SUM(D39:H39) -> 0 | J39: =IFERROR(IF(AND(D39>0,H39>0),(H39/D39)^(1/4)-1,0)*100,0) -> 0
A40: 4 | I40: =SUM(D40:H40) -> 0 | J40: =IFERROR(IF(AND(D40>0,H40>0),(H40/D40)^(1/4)-1,0)*100,0) -> 0
A41: 5 | I41: =SUM(D41:H41) -> 0 | J41: =IFERROR(IF(AND(D41>0,H41>0),(H41/D41)^(1/4)-1,0)*100,0) -> 0
A42: 6 | I42: =SUM(D42:H42) -> 0 | J42: =IFERROR(IF(AND(D42>0,H42>0),(H42/D42)^(1/4)-1,0)*100,0) -> 0
A43: 7 | I43: =SUM(D43:H43) -> 0 | J43: =IFERROR(IF(AND(D43>0,H43>0),(H43/D43)^(1/4)-1,0)*100,0) -> 0
A44: 8 | I44: =SUM(D44:H44) -> 0 | J44: =IFERROR(IF(AND(D44>0,H44>0),(H44/D44)^(1/4)-1,0)*100,0) -> 0
A45: 9 | I45: =SUM(D45:H45) -> 0 | J45: =IFERROR(IF(AND(D45>0,H45>0),(H45/D45)^(1/4)-1,0)*100,0) -> 0
A46: 10 | I46: =SUM(D46:H46) -> 0 | J46: =IFERROR(IF(AND(D46>0,H46>0),(H46/D46)^(1/4)-1,0)*100,0) -> 0
A47: 11 | I47: =SUM(D47:H47) -> 0 | J47: =IFERROR(IF(AND(D47>0,H47>0),(H47/D47)^(1/4)-1,0)*100,0) -> 0
A48: 12 | I48: =SUM(D48:H48) -> 0 | J48: =IFERROR(IF(AND(D48>0,H48>0),(H48/D48)^(1/4)-1,0)*100,0) -> 0
... A56: 20 | I56: =SUM(D56:H56) -> 0 | J56: =IFERROR(IF(AND(D56>0,H56>0),(H56/D56)^(1/4)-1,0)*100,0) -> 0

Sheet 2. PPP & per-FTE Calc
A1: Research Income — PPP Conversion & per-FTE Calculation
A2: Local Currency → PPP-USD → divided by Staff FTE = Research Income per Staff (PPP-USD)
A3: S.No. | B3: University Name | C3: Country | D3: Research Income (Local Currency) | E3: PPP Factor (World Bank) | F3: Research Income (PPP-USD) | G3: Academic Staff FTE | H3: Research Income per Staff (PPP-USD) | I3: Z-Score | J3: Normalized Score (0–100)
A4: 1 | D4: ='1. Research Income'!I4 -> 0 | F4: =IF(E4>0,D4/E4,0) -> 0 | G4: ='3. Staff FTE'!J4 -> 0 | H4: =IF(G4>0,F4/G4,0) -> 0 | I4: =IFERROR((H4-AVERAGE($H$4:$H$33))/STDEV($H$4:$H$33),0) -> 0 | J4: =IFERROR(IF(MAX($H$4:$H$33)-MIN($H$4:$H$33)>0,(H4-MIN($H$4:$H$33))/(MAX($H$4:$H$33)-MIN($H$4:$H$33))*100,0),0) -> 0
A5: 2 | D5: ='1. Research Income'!I5 -> 0 | F5: =IF(E5>0,D5/E5,0) -> 0 | G5: ='3. Staff FTE'!J5 -> 0 | H5: =IF(G5>0,F5/G5,0) -> 0 | I5: =IFERROR((H5-AVERAGE($H$4:$H$33))/STDEV($H$4:$H$33),0) -> 0 | J5: =IFERROR(IF(MAX($H$4:$H$33)-MIN($H$4:$H$33)>0,(H5-MIN($H$4:$H$33))/(MAX($H$4:$H$33)-MIN($H$4:$H$33))*100,0),0) -> 0
A6: 3 | D6: ='1. Research Income'!I6 -> 0 | F6: =IF(E6>0,D6/E6,0) -> 0 | G6: ='3. Staff FTE'!J6 -> 0 | H6: =IF(G6>0,F6/G6,0) -> 0 | I6: =IFERROR((H6-AVERAGE($H$4:$H$33))/STDEV($H$4:$H$33),0) -> 0 | J6: =IFERROR(IF(MAX($H$4:$H$33)-MIN($H$4:$H$33)>0,(H6-MIN($H$4:$H$33))/(MAX($H$4:$H$33)-MIN($H$4:$H$33))*100,0),0) -> 0
A7: 4 | D7: ='1. Research Income'!I7 -> 0 | F7: =IF(E7>0,D7/E7,0) -> 0 | G7: ='3. Staff FTE'!J7 -> 0 | H7: =IF(G7>0,F7/G7,0) -> 0 | I7: =IFERROR((H7-AVERAGE($H$4:$H$33))/STDEV($H$4:$H$33),0) -> 0 | J7: =IFERROR(IF(MAX($H$4:$H$33)-MIN($H$4:$H$33)>0,(H7-MIN($H$4:$H$33))/(MAX($H$4:$H$33)-MIN($H$4:$H$33))*100,0),0) -> 0
A8: 5 | D8: ='1. Research Income'!I8 -> 0 | F8: =IF(E8>0,D8/E8,0) -> 0 | G8: ='3. Staff FTE'!J8 -> 0 | H8: =IF(G8>0,F8/G8,0) -> 0 | I8: =IFERROR((H8-AVERAGE($H$4:$H$33))/STDEV($H$4:$H$33),0) -> 0 | J8: =IFERROR(IF(MAX($H$4:$H$33)-MIN($H$4:$H$33)>0,(H8-MIN($H$4:$H$33))/(MAX($H$4:$H$33)-MIN($H$4:$H$33))*100,0),0) -> 0
A9: 6 | D9: ='1. Research Income'!I9 -> 0 | F9: =IF(E9>0,D9/E9,0) -> 0 | G9: ='3. Staff FTE'!J9 -> 0 | H9: =IF(G9>0,F9/G9,0) -> 0 | I9: =IFERROR((H9-AVERAGE($H$4:$H$33))/STDEV($H$4:$H$33),0) -> 0 | J9: =IFERROR(IF(MAX($H$4:$H$33)-MIN($H$4:$H$33)>0,(H9-MIN($H$4:$H$33))/(MAX($H$4:$H$33)-MIN($H$4:$H$33))*100,0),0) -> 0
A10: 7 | D10: ='1. Research Income'!I10 -> 0 | F10: =IF(E10>0,D10/E10,0) -> 0 | G10: ='3. Staff FTE'!J10 -> 0 | H10: =IF(G10>0,F10/G10,0) -> 0 | I10: =IFERROR((H10-AVERAGE($H$4:$H$33))/STDEV($H$4:$H$33),0) -> 0 | J10: =IFERROR(IF(MAX($H$4:$H$33)-MIN($H$4:$H$33)>0,(H10-MIN($H$4:$H$33))/(MAX($H$4:$H$33)-MIN($H$4:$H$33))*100,0),0) -> 0
A11: 8 | D11: ='1. Research Income'!I11 -> 0 | F11: =IF(E11>0,D11/E11,0) -> 0 | G11: ='3. Staff FTE'!J11 -> 0 | H11: =IF(G11>0,F11/G11,0) -> 0 | I11: =IFERROR((H11-AVERAGE($H$4:$H$33))/STDEV($H$4:$H$33),0) -> 0 | J11: =IFERROR(IF(MAX($H$4:$H$33)-MIN($H$4:$H$33)>0,(H11-MIN($H$4:$H$33))/(MAX($H$4:$H$33)-MIN($H$4:$H$33))*100,0),0) -> 0
A12: 9 | D12: ='1. Research Income'!I12 -> 0 | F12: =IF(E12>0,D12/E12,0) -> 0 | G12: ='3. Staff FTE'!J12 -> 0 | H12: =IF(G12>0,F12/G12,0) -> 0 | I12: =IFERROR((H12-AVERAGE($H$4:$H$33))/STDEV($H$4:$H$33),0) -> 0 | J12: =IFERROR(IF(MAX($H$4:$H$33)-MIN($H$4:$H$33)>0,(H12-MIN($H$4:$H$33))/(MAX($H$4:$H$33)-MIN($H$4:$H$33))*100,0),0) -> 0
A13: 10 | D13: ='1. Research Income'!I13 -> 0 | F13: =IF(E13>0,D13/E13,0) -> 0 | G13: ='3. Staff FTE'!J13 -> 0 | H13: =IF(G13>0,F13/G13,0) -> 0 | I13: =IFERROR((H13-AVERAGE($H$4:$H$33))/STDEV($H$4:$H$33),0) -> 0 | J13: =IFERROR(IF(MAX($H$4:$H$33)-MIN($H$4:$H$33)>0,(H13-MIN($H$4:$H$33))/(MAX($H$4:$H$33)-MIN($H$4:$H$33))*100,0),0) -> 0
A14: 11 | D14: ='1. Research Income'!I14 -> 0 | F14: =IF(E14>0,D14/E14,0) -> 0 | G14: ='3. Staff FTE'!J14 -> 0 | H14: =IF(G14>0,F14/G14,0) -> 0 | I14: =IFERROR((H14-AVERAGE($H$4:$H$33))/STDEV($H$4:$H$33),0) -> 0 | J14: =IFERROR(IF(MAX($H$4:$H$33)-MIN($H$4:$H$33)>0,(H14-MIN($H$4:$H$33))/(MAX($H$4:$H$33)-MIN($H$4:$H$33))*100,0),0) -> 0
A15: 12 | D15: ='1. Research Income'!I15 -> 0 | F15: =IF(E15>0,D15/E15,0) -> 0 | G15: ='3. Staff FTE'!J15 -> 0 | H15: =IF(G15>0,F15/G15,0) -> 0 | I15: =IFERROR((H15-AVERAGE($H$4:$H$33))/STDEV($H$4:$H$33),0) -> 0 | J15: =IFERROR(IF(MAX($H$4:$H$33)-MIN($H$4:$H$33)>0,(H15-MIN($H$4:$H$33))/(MAX($H$4:$H$33)-MIN($H$4:$H$33))*100,0),0) -> 0
... A33: 30 | D33: ='1. Research Income'!I33 -> 0 | F33: =IF(E33>0,D33/E33,0) -> 0 | G33: ='3. Staff FTE'!J33 -> 0 | H33: =IF(G33>0,F33/G33,0) -> 0 | I33: =IFERROR((H33-AVERAGE($H$4:$H$33))/STDEV($H$4:$H$33),0) -> 0 | J33: =IFERROR(IF(MAX($H$4:$H$33)-MIN($H$4:$H$33)>0,(H33-MIN($H$4:$H$33))/(MAX($H$4:$H$33)-MIN($H$4:$H$33))*100,0),0) -> 0
A35: Summary Statistics
A36: Avg Research Income per Staff (PPP-USD) | F36: =IF(COUNTA(H4:H33)>0,AVERAGE(H4:H33),0) -> 0
A37: Highest | F37: =MAX(H4:H33) -> 0
A38: Lowest | F38: =MIN(H4:H33) -> 0
A39: Median | F39: =MEDIAN(H4:H33) -> 0
A40: Total Research Income (All Univ, PPP-USD) | F40: =SUM(F4:F33) -> 0

Sheet 3. Staff FTE
A1: Academic Staff FTE — Must Match All Other Indicators
A2: SAME FTE used for SSR (4.5%), Doctorates/Staff (5.5%), Inst. Income (2.5%), AND Research Income (5.5%)
A3: S.No. | B3: University Name | C3: Country | D3: Professors (FTE) | E3: Assoc. Prof (FTE) | F3: Asst. Prof (FTE) | G3: Lecturers (FTE) | H3: Res. Fellows (Teaching) FTE | I3: Other Teaching FTE | J3: Total Academic Staff FTE | K3: Reporting Year
A4: 1 | J4: =SUM(D4:I4) -> 0
A5: 2 | J5: =SUM(D5:I5) -> 0
A6: 3 | J6: =SUM(D6:I6) -> 0
A7: 4 | J7: =SUM(D7:I7) -> 0
A8: 5 | J8: =SUM(D8:I8) -> 0
A9: 6 | J9: =SUM(D9:I9) -> 0
A10: 7 | J10: =SUM(D10:I10) -> 0
A11: 8 | J11: =SUM(D11:I11) -> 0
A12: 9 | J12: =SUM(D12:I12) -> 0
A13: 10 | J13: =SUM(D13:I13) -> 0
A14: 11 | J14: =SUM(D14:I14) -> 0
A15: 12 | J15: =SUM(D15:I15) -> 0
... A33: 30 | J33: =SUM(D33:I33) -> 0

Sheet 4. Dept-Level Income
A1: Department-Level Research Income — Identifying Strengths & Gaps
A2: Granular view: which departments win the most grants | Prioritize support where income is lowest
A3: S.No. | B3: Department / School | C3: Faculty / College | D3: Govt Grants | E3: Industry R&D | F3: Intl Collab | G3: Total Research Income | H3: Staff FTE | I3: Income per Staff (Local Currency)
A4: 1 | G4: =SUM(D4:F4) -> 0 | I4: =IF(H4>0,G4/H4,0) -> 0
A5: 2 | G5: =SUM(D5:F5) -> 0 | I5: =IF(H5>0,G5/H5,0) -> 0
A6: 3 | G6: =SUM(D6:F6) -> 0 | I6: =IF(H6>0,G6/H6,0) -> 0
A7: 4 | G7: =SUM(D7:F7) -> 0 | I7: =IF(H7>0,G7/H7,0) -> 0
A8: 5 | G8: =SUM(D8:F8) -> 0 | I8: =IF(H8>0,G8/H8,0) -> 0
A9: 6 | G9: =SUM(D9:F9) -> 0 | I9: =IF(H9>0,G9/H9,0) -> 0
A10: 7 | G10: =SUM(D10:F10) -> 0 | I10: =IF(H10>0,G10/H10,0) -> 0
A11: 8 | G11: =SUM(D11:F11) -> 0 | I11: =IF(H11>0,G11/H11,0) -> 0
A12: 9 | G12: =SUM(D12:F12) -> 0 | I12: =IF(H12>0,G12/H12,0) -> 0
A13: 10 | G13: =SUM(D13:F13) -> 0 | I13: =IF(H13>0,G13/H13,0) -> 0
A14: 11 | G14: =SUM(D14:F14) -> 0 | I14: =IF(H14>0,G14/H14,0) -> 0
A15: 12 | G15: =SUM(D15:F15) -> 0 | I15: =IF(H15>0,G15/H15,0) -> 0
... A43: 40 | G43: =SUM(D43:F43) -> 0 | I43: =IF(H43>0,G43/H43,0) -> 0

Sheet 5. Grant Pipeline
A1: Grant Proposal Pipeline — Submitted, Awarded, Success Rate
A2: Tracks competitive grant-winning performance | Success rate = key indicator of research competitiveness
A3: S.No. | B3: University Name | C3: Country | D3: Proposals Submitted (Year) | E3: Proposals Awarded | F3: Success Rate (%) | G3: Total Value Awarded (Local Currency) | H3: Avg Grant Size | I3: Reporting Year
A4: 1 | F4: =IF(D4>0,E4/D4*100,0) -> 0 | H4: =IF(E4>0,G4/E4,0) -> 0
A5: 2 | F5: =IF(D5>0,E5/D5*100,0) -> 0 | H5: =IF(E5>0,G5/E5,0) -> 0
A6: 3 | F6: =IF(D6>0,E6/D6*100,0) -> 0 | H6: =IF(E6>0,G6/E6,0) -> 0
A7: 4 | F7: =IF(D7>0,E7/D7*100,0) -> 0 | H7: =IF(E7>0,G7/E7,0) -> 0
A8: 5 | F8: =IF(D8>0,E8/D8*100,0) -> 0 | H8: =IF(E8>0,G8/E8,0) -> 0
A9: 6 | F9: =IF(D9>0,E9/D9*100,0) -> 0 | H9: =IF(E9>0,G9/E9,0) -> 0
A10: 7 | F10: =IF(D10>0,E10/D10*100,0) -> 0 | H10: =IF(E10>0,G10/E10,0) -> 0
A11: 8 | F11: =IF(D11>0,E11/D11*100,0) -> 0 | H11: =IF(E11>0,G11/E11,0) -> 0
A12: 9 | F12: =IF(D12>0,E12/D12*100,0) -> 0 | H12: =IF(E12>0,G12/E12,0) -> 0
A13: 10 | F13: =IF(D13>0,E13/D13*100,0) -> 0 | H13: =IF(E13>0,G13/E13,0) -> 0
A14: 11 | F14: =IF(D14>0,E14/D14*100,0) -> 0 | H14: =IF(E14>0,G14/E14,0) -> 0
A15: 12 | F15: =IF(D15>0,E15/D15*100,0) -> 0 | H15: =IF(E15>0,G15/E15,0) -> 0
... A33: 30 | F33: =IF(D33>0,E33/D33*100,0) -> 0 | H33: =IF(E33>0,G33/E33,0) -> 0
A35: Grant Pipeline by Funding Agency
A36: S.No. | B36: Funding Agency | C36: Type (Govt/Industry/Intl/Foundation) | D36: Proposals Submitted | E36: Proposals Awarded | F36: Success Rate (%) | G36: Value Awarded | H36: Avg Grant Size | I36: University Name
A37: 1 | F37: =IF(D37>0,E37/D37*100,0) -> 0 | H37: =IF(E37>0,G37/E37,0) -> 0
A38: 2 | F38: =IF(D38>0,E38/D38*100,0) -> 0 | H38: =IF(E38>0,G38/E38,0) -> 0
A39: 3 | F39: =IF(D39>0,E39/D39*100,0) -> 0 | H39: =IF(E39>0,G39/E39,0) -> 0
A40: 4 | F40: =IF(D40>0,E40/D40*100,0) -> 0 | H40: =IF(E40>0,G40/E40,0) -> 0
A41: 5 | F41: =IF(D41>0,E41/D41*100,0) -> 0 | H41: =IF(E41>0,G41/E41,0) -> 0
A42: 6 | F42: =IF(D42>0,E42/D42*100,0) -> 0 | H42: =IF(E42>0,G42/E42,0) -> 0
A43: 7 | F43: =IF(D43>0,E43/D43*100,0) -> 0 | H43: =IF(E43>0,G43/E43,0) -> 0
A44: 8 | F44: =IF(D44>0,E44/D44*100,0) -> 0 | H44: =IF(E44>0,G44/E44,0) -> 0
A45: 9 | F45: =IF(D45>0,E45/D45*100,0) -> 0 | H45: =IF(E45>0,G45/E45,0) -> 0
A46: 10 | F46: =IF(D46>0,E46/D46*100,0) -> 0 | H46: =IF(E46>0,G46/E46,0) -> 0
A47: 11 | F47: =IF(D47>0,E47/D47*100,0) -> 0 | H47: =IF(E47>0,G47/E47,0) -> 0
A48: 12 | F48: =IF(D48>0,E48/D48*100,0) -> 0 | H48: =IF(E48>0,G48/E48,0) -> 0
... A66: 30 | F66: =IF(D66>0,E66/D66*100,0) -> 0 | H66: =IF(E66>0,G66/E66,0) -> 0

Sheet 6. Income Rules
A1: Research Income — What Counts & What Doesn't (THE Definition)
A2: CRITICAL: This is RESEARCH income only — NOT total institutional income
A3: # | B3: Category | C3: Revenue Item | D3: Include / Exclude | E3: Notes
A4: 1 | B4: Research | C4: Competitive govt research grants (DST, SERB, DBT, ICMR, CSIR, MHRD-research) | D4: Include | E4: Core research funding
A5: 2 | B5: Research | C5: International research grants (EU, UNDP, World Bank, bilateral R&D) | D5: Include | E5: Externally sourced
A6: 3 | B6: Research | C6: Industry-sponsored R&D contracts | D6: Include | E6: Commissioned research for industry
A7: 4 | B7: Research | C7: Foundation / philanthropy grants FOR RESEARCH | D7: Include | E7: Wellcome, BMGF, Ford — research-specific
A8: 5 | B8: Research | C8: Commissioned / contract research (other external) | D8: Include | E8: Third-party funded research
A9: 6 | B9: Research | C9: Research component of block grants (if separately identified) | D9: Include | E9: Only the earmarked research portion
A10: 7 | B10: NOT Research | C10: Government block grant (general / unrestricted) | D10: Exclude | E10: Goes to Institutional Income (2.5%)
A11: 8 | B11: NOT Research | C11: Tuition fees | D11: Exclude | E11: Not research income
A12: 9 | B12: NOT Research | C12: Consultancy / technical services revenue | D12: Exclude | E12: Applied services, not new knowledge creation
A13: 10 | B13: NOT Research | C13: Internal university research allocations | D13: Exclude | E13: Not externally sourced
A14: 11 | B14: NOT Research | C14: Endowment / investment returns | D14: Exclude | E14: Goes to Institutional Income (2.5%)
A15: 12 | B15: NOT Research | C15: Philanthropy for non-research purposes (scholarships, buildings) | D15: Exclude | E15: Not research
... A21: 18 | B21: Ambiguous | C21: Fellowship stipends for PhD students | D21: Conditional | E21: Include if part of a research grant; exclude if standalone scholarship

Sheet 7. Action Plan
A1: Research Income Growth — Strategic Action Plan
A3: # | B3: University Name | C3: Action Item | D3: Phase | E3: Status | F3: Target Date | G3: Remarks
A4: 1 | C4: Establish Grant Support Office (pre-award + post-award) | D4: 1 (0–6mo)
A5: 2 | C5: Train faculty on competitive proposal writing (DST/SERB/DBT/ERC/NSF) | D5: 1 (0–6mo)
A6: 3 | C6: Audit current grant portfolio and identify growth areas | D6: 1 (0–6mo)
A7: 4 | C7: Build database of funding opportunities with deadline calendar | D7: 1 (0–6mo)
A8: 5 | C8: Target 5+ new industry-sponsored R&D contracts per year | D8: 2 (6–18mo)
A9: 6 | C9: Pursue 3+ international research collaboration grants | D9: 2 (6–18mo)
A10: 7 | C10: Apply to foundation grants (Wellcome, BMGF, Ford) in focus areas | D10: 2 (6–18mo)
A11: 8 | C11: Establish grant-writing mentorship: senior faculty coaching juniors | D11: 2 (6–18mo)
A12: 9 | C12: Set departmental research income targets linked to faculty appraisal | D12: 2 (6–18mo)
A13: 10 | C13: Create incentive structure: research income rewards / recognition | D13: 2 (6–18mo)
A14: 11 | C14: Grow research income by 25–40% from Year 1 baseline (PPP-adjusted) | D14: 3 (18–36mo)
A15: 12 | C15: Achieve grant success rate >30% across all agencies | D15: 3 (18–36mo)
A16: 13 | C16: Diversify across 4+ funding source categories | D16: 3 (18–36mo)
A18: Progress
A19: Completed | D19: =COUNTIF(E4:E16,"Done") -> 0
A20: In Progress | D20: =COUNTIF(E4:E16,"IP") -> 0
A21: Completion (%) | D21: =IFERROR(COUNTIF(E4:E16,"Done")/13*100,0) -> 0

Sheet 8. Benchmarking
A1: Benchmarking — Research Income (PPP per FTE)
A3: S.No. | B3: University / Benchmark | C3: Research Income (PPP-USD) | D3: Staff FTE | E3: Income/FTE | F3: Score (0–100) | G3: Peer Group
A4: 1 | B4: Your Institution | G4: Target
A5: 2 | B5: Global Top 10 Average | G5: Aspirational
A6: 3 | B6: National Average | G6: National
A7: 4 | B7: Peer Group Average | G7: Peer
A8: 1
A9: 2
A10: 3
A11: 4
A12: 5
A13: 6
A14: 7
A15: 8
A16: 9
A17: 10
A18: 11
A19: 12
... A22: 15

Sheet 9. Risk Assessment
A1: Research Income — Risk Assessment
A3: # | B3: Risk | C3: Level | D3: Impact | E3: Mitigation | F3: Owner
A4: 1 | B4: Low grant success rate | C4: 🟡 Medium | D4: Few awards despite proposals; income stagnates | E4: Proposal writing training; internal peer review before submission; target aligned agencies
A5: 2 | B5: Over-reliance on one funding source | C5: 🟡 Medium | D5: Vulnerable to agency budget cuts | E5: Diversify across govt, industry, intl, foundation sources
A6: 3 | B6: Consultancy income counted as research | C6: 🔴 High | D6: Non-research revenue inflates numerator; audit risk | E6: Strictly separate consultancy from sponsored research in finance system
A7: 4 | B7: Block grants counted as research income | C7: 🔴 High | D7: Unrestricted grants not eligible; audit penalty | E7: Only count earmarked research portions with project deliverables
A8: 5 | B8: Incorrect PPP factor | C8: 🔴 High | D8: Income inflated/deflated vs peers | E8: Verify World Bank PPP for exact year; document source
A9: 6 | B9: Staff FTE mismatch across indicators | C9: 🔴 High | D9: Different FTE denominators across pillars | E9: Use SAME FTE for ALL indicators: SSR, Doctorates/Staff, Inst Income, Research Income
A10: 7 | B10: Faculty not applying for grants | C10: 🟡 Medium | D10: Low proposal volume; missed opportunities | E10: Incentives, protected time for proposals, grant-writing support
A11: 8 | B11: Budget constraints limiting research investment | C11: 🟡 Medium | D11: Cannot provide matching funds required by some agencies | E11: Phased investment; identify agencies without matching requirements

Sheet 10. Data Quality Audit
A1: Research Income (PPP) — Data Quality & Audit Checklist
A2: Validation checks for this indicator (5.5% of total WUR score)
A3: # | B3: Quality Check | C3: Description | D3: Status (✓/✗/IP) | E3: Date | F3: Reviewer
A4: 1 | B4: Research-only income verification | C4: ALL items counted are externally-sourced RESEARCH funding; no tuition, consultancy, block grants, endowment
A5: 2 | B5: Audited accounts linkage | C5: Research income figures traceable to specific line items in audited financial statements
A6: 3 | B6: Consultancy income excluded | C6: Consultancy / technical services revenue NOT included in research income
A7: 4 | B7: Block grant separation | C7: General block grants excluded; only earmarked research portions with deliverables included
A8: 5 | B8: Internal allocations excluded | C8: University's own internal research budget allocations NOT counted
A9: 6 | B9: PPP rate accuracy | C9: World Bank PPP conversion factor matches published rate for exact submission year
A10: 7 | B10: PPP source documented | C10: Year, source, and specific PPP rate documented in submission
A11: 8 | B11: Academic Staff FTE consistency | C11: SAME Staff FTE used here AND in SSR (4.5%), Doctorates/Staff (5.5%), Inst Income (2.5%)
A12: 9 | B12: FTE THE-compliant | C12: Staff FTE per THE definition; research-only, admin, technical staff excluded
A13: 10 | B13: Income per FTE calculation | C13: Research Income PPP-USD ÷ Staff FTE verified independently by 2 reviewers
A14: 11 | B14: Source breakdown reconciliation | C14: Sum of 5 source categories = total research income (within ±1% tolerance)
A15: 12 | B15: Fiscal year consistency | C15: Same fiscal year definition used across all indicators and all years
... A23: 20 | B23: Reproducibility test | C23: Income per FTE independently reproducible from audited accounts + HR records within ±2%
