Workbook

Sheet Methodology Overview
A1: THE WUR — Teaching (29.5%) → Institutional Income Scaled for PPP (2.5%)
A2: Proxy for Overall Teaching Resources & Investment | PPP-Adjusted per FTE | 2.5% of Total WUR Score
A4: # | B4: Component | C4: Description & Methodology | D4: Weight
A5: 1 | B5: Institutional Income (PPP-Scaled) | C5: Total institutional income (revenue) normalized by academic staff FTE AND adjusted for Purchasing Power Parity (PPP). Signals the overall financial health and investment capacity available for the teaching environment. THE uses this as a broad proxy for teaching resources — institutions with higher per-capita income can invest more in facilities, technology, learning materials, and faculty development. | D5: 2.5% of WUR
A6: 2 | B6: Total Institutional Income (Numerator) | C6: Aggregate annual revenue from ALL sources: government block grants, tuition fees, research grants, industry income, endowment returns, philanthropy/donations, hospital/clinical income (if part of university), consultancy revenue, and other operating income. THE requests the most recent audited fiscal year. Excludes: capital grants for construction (one-time), proceeds from asset sales. | D6: Numerator
A7: 3 | B7: Academic Staff FTE (Denominator) | C7: Same THE-compliant FTE definition used across all Teaching sub-indicators. Full-time equivalent academic staff with teaching duties. Professors, associate/assistant professors, lecturers, research fellows WITH teaching. Excludes admin, technical, support, research-only staff. | D7: Denominator
A8: 4 | B8: PPP Adjustment | C8: All income figures converted to USD using World Bank Purchasing Power Parity (PPP) conversion factors for the relevant year. PPP adjusts for cost-of-living differences between countries — $1 buys different amounts in India vs USA vs Switzerland. Without PPP, institutions in high-cost countries would be artificially advantaged. THE uses IMF/World Bank PPP rates. | D8: Normalization
A9: 5 | B9: Scoring Logic | C9: THE computes: (Total Income in PPP-USD) ÷ Academic Staff FTE → z-scored across all ranked universities. Higher income per staff = higher z-score = better rank. This indicator is rated 🟢 Easy to collect but 🟡 Moderate to improve (depends on revenue diversification and institutional funding model). | D9: Normalization
A10: 6 | B10: Context: Teaching Pillar | C10: Teaching (29.5%) = Teaching Reputation (15%) + Staff-to-Student Ratio (4.5%) + Doctorates Awarded per Staff (5.5%) + Doctorate-to-Bachelor's Ratio (2%) + Institutional Income (2.5%). At 2.5%, this is the smallest Teaching sub-indicator but still matters for overall pillar score. | D10: 2.5% of 29.5%
A12: Improvement Strategies
A13: • Diversify revenue streams: industry partnerships, consultancy, philanthropy, endowments, executive education.
A14: • Pursue international collaborations that bring grant income and co-funding.
A15: • Establish an institutional advancement / fundraising office for donor cultivation.
A16: • Maximize government grant capture through competitive proposal submissions.
A17: • Launch fee-based executive education / continuing professional development programmes.
A18: • Build an alumni engagement programme for philanthropic giving.
A19: • Difficulty: 🟡 Moderate (1–3 years). Revenue diversification takes time but data collection is straightforward (🟢 Easy).

Sheet 1. Total Income
A1: Total Institutional Income — Revenue by Source (Most Recent Fiscal Year)
A2: All revenue sources | Local currency → converted to PPP-USD | Audited figures only
A3: S.No. | B3: University Name | C3: Country | D3: Govt Block Grants / Funding (Local Currency) | E3: Tuition & Student Fees | F3: Research Grants & Contracts | G3: Industry / Corporate Income | H3: Endowment / Investment Returns | I3: Philanthropy / Donations / CSR | J3: Other Operating Income | K3: Total Institutional Income (Local Currency)
A4: 1 | K4: =SUM(D4:J4) -> 0
A5: 2 | K5: =SUM(D5:J5) -> 0
A6: 3 | K6: =SUM(D6:J6) -> 0
A7: 4 | K7: =SUM(D7:J7) -> 0
A8: 5 | K8: =SUM(D8:J8) -> 0
A9: 6 | K9: =SUM(D9:J9) -> 0
A10: 7 | K10: =SUM(D10:J10) -> 0
A11: 8 | K11: =SUM(D11:J11) -> 0
A12: 9 | K12: =SUM(D12:J12) -> 0
A13: 10 | K13: =SUM(D13:J13) -> 0
A14: 11 | K14: =SUM(D14:J14) -> 0
A15: 12 | K15: =SUM(D15:J15) -> 0
... A33: 30 | K33: =SUM(D33:J33) -> 0
A35: Supplementary Revenue Detail (If Applicable)
A36: S.No. | B36: University Name | C36: Country | D36: Hospital / Clinical Revenue | E36: Consultancy & Technical Services | F36: Executive Education / CPD Revenue | G36: Facility Rental / Usage Income | H36: Alumni Fund Contributions | I36: International Student Fee Premium | J36: Other Supplementary Income | K36: Total Supplementary
A37: 1 | K37: =SUM(D37:J37) -> 0
A38: 2 | K38: =SUM(D38:J38) -> 0
A39: 3 | K39: =SUM(D39:J39) -> 0
A40: 4 | K40: =SUM(D40:J40) -> 0
A41: 5 | K41: =SUM(D41:J41) -> 0
A42: 6 | K42: =SUM(D42:J42) -> 0
A43: 7 | K43: =SUM(D43:J43) -> 0
A44: 8 | K44: =SUM(D44:J44) -> 0
A45: 9 | K45: =SUM(D45:J45) -> 0
A46: 10 | K46: =SUM(D46:J46) -> 0
A47: 11 | K47: =SUM(D47:J47) -> 0
A48: 12 | K48: =SUM(D48:J48) -> 0
... A56: 20 | K56: =SUM(D56:J56) -> 0

Sheet 2. PPP Conversion
A1: PPP Conversion — Local Currency to PPP-Adjusted USD
A2: World Bank PPP conversion factors | Income (Local) ÷ PPP Factor = Income (PPP-USD)
A3: S.No. | B3: University Name | C3: Country | D3: Total Income (Local Currency) | E3: PPP Conversion Factor (World Bank) | F3: Total Income (PPP-USD) | G3: Income per Staff FTE (PPP-USD) | H3: Reporting Year
A4: 1 | D4: ='1. Total Income'!K4 -> 0 | F4: =IF(E4>0,D4/E4,0) -> 0 | G4: =IF('3. Staff FTE'!J4>0,F4/'3. Staff FTE'!J4,0) -> 0
A5: 2 | D5: ='1. Total Income'!K5 -> 0 | F5: =IF(E5>0,D5/E5,0) -> 0 | G5: =IF('3. Staff FTE'!J5>0,F5/'3. Staff FTE'!J5,0) -> 0
A6: 3 | D6: ='1. Total Income'!K6 -> 0 | F6: =IF(E6>0,D6/E6,0) -> 0 | G6: =IF('3. Staff FTE'!J6>0,F6/'3. Staff FTE'!J6,0) -> 0
A7: 4 | D7: ='1. Total Income'!K7 -> 0 | F7: =IF(E7>0,D7/E7,0) -> 0 | G7: =IF('3. Staff FTE'!J7>0,F7/'3. Staff FTE'!J7,0) -> 0
A8: 5 | D8: ='1. Total Income'!K8 -> 0 | F8: =IF(E8>0,D8/E8,0) -> 0 | G8: =IF('3. Staff FTE'!J8>0,F8/'3. Staff FTE'!J8,0) -> 0
A9: 6 | D9: ='1. Total Income'!K9 -> 0 | F9: =IF(E9>0,D9/E9,0) -> 0 | G9: =IF('3. Staff FTE'!J9>0,F9/'3. Staff FTE'!J9,0) -> 0
A10: 7 | D10: ='1. Total Income'!K10 -> 0 | F10: =IF(E10>0,D10/E10,0) -> 0 | G10: =IF('3. Staff FTE'!J10>0,F10/'3. Staff FTE'!J10,0) -> 0
A11: 8 | D11: ='1. Total Income'!K11 -> 0 | F11: =IF(E11>0,D11/E11,0) -> 0 | G11: =IF('3. Staff FTE'!J11>0,F11/'3. Staff FTE'!J11,0) -> 0
A12: 9 | D12: ='1. Total Income'!K12 -> 0 | F12: =IF(E12>0,D12/E12,0) -> 0 | G12: =IF('3. Staff FTE'!J12>0,F12/'3. Staff FTE'!J12,0) -> 0
A13: 10 | D13: ='1. Total Income'!K13 -> 0 | F13: =IF(E13>0,D13/E13,0) -> 0 | G13: =IF('3. Staff FTE'!J13>0,F13/'3. Staff FTE'!J13,0) -> 0
A14: 11 | D14: ='1. Total Income'!K14 -> 0 | F14: =IF(E14>0,D14/E14,0) -> 0 | G14: =IF('3. Staff FTE'!J14>0,F14/'3. Staff FTE'!J14,0) -> 0
A15: 12 | D15: ='1. Total Income'!K15 -> 0 | F15: =IF(E15>0,D15/E15,0) -> 0 | G15: =IF('3. Staff FTE'!J15>0,F15/'3. Staff FTE'!J15,0) -> 0
... A33: 30 | D33: ='1. Total Income'!K33 -> 0 | F33: =IF(E33>0,D33/E33,0) -> 0 | G33: =IF('3. Staff FTE'!J33>0,F33/'3. Staff FTE'!J33,0) -> 0
A35: PPP Conversion Factor Reference (Select Countries)
A36: # | B36: Country | C36: ISO Code | D36: PPP Factor (LCU per Intl $) | E36: Source | F36: Year
A37: 1 | B37: India | C37: IND | D37: 22.88 | E37: World Bank ICP | F37: 2023
A38: 2 | B38: United States | C38: USA | D38: 1.00 | E38: Baseline | F38: 2023
A39: 3 | B39: United Kingdom | C39: GBR | D39: 0.69 | E39: World Bank ICP | F39: 2023
A40: 4 | B40: China | C40: CHN | D40: 4.19 | E40: World Bank ICP | F40: 2023
A41: 5 | B41: Germany | C41: DEU | D41: 0.74 | E41: World Bank ICP | F41: 2023
A42: 6 | B42: Japan | C42: JPN | D42: 97.69 | E42: World Bank ICP | F42: 2023
A43: 7 | B43: Australia | C43: AUS | D43: 1.48 | E43: World Bank ICP | F43: 2023
A44: 8 | B44: Canada | C44: CAN | D44: 1.21 | E44: World Bank ICP | F44: 2023
A45: 9 | B45: Singapore | C45: SGP | D45: 0.84 | E45: World Bank ICP | F45: 2023
A46: 10 | B46: South Korea | C46: KOR | D46: 855.76 | E46: World Bank ICP | F46: 2023
A47: 11 | B47: Brazil | C47: BRA | D47: 2.55 | E47: World Bank ICP | F47: 2023
A48: 12 | B48: South Africa | C48: ZAF | D48: 7.40 | E48: World Bank ICP | F48: 2023

Sheet 3. Staff FTE
A1: Academic Staff FTE — Same Definition as Staff-to-Student Ratio & Doctorates-per-Staff
A2: THE-compliant: professors, assoc/asst prof, lecturers, research fellows with teaching | Must match other indicators
A3: S.No. | B3: University Name | C3: Country | D3: Professors (FTE) | E3: Assoc. Prof (FTE) | F3: Asst. Prof (FTE) | G3: Lecturers (FTE) | H3: Res. Fellows (Teaching) FTE | I3: Other Teaching FTE | J3: Total Academic Staff FTE | K3: Reporting Year
A4: 1 | J4: =SUM(D4:I4) -> 0
A5: 2 | J5: =SUM(D5:I5) -> 0
A6: 3 | J6: =SUM(D6:I6) -> 0
A7: 4 | J7: =SUM(D7:I7) -> 0
A8: 5 | J8: =SUM(D8:I8) -> 0
A9: 6 | J9: =SUM(D9:I9) -> 0
A10: 7 | J10: =SUM(D10:I10) -> 0
A11: 8 | J11: =SUM(D11:I11) -> 0
A12: 9 | J12: =SUM(D12:I12) -> 0
A13: 10 | J13: =SUM(D13:I13) -> 0
A14: 11 | J14: =SUM(D14:I14) -> 0
A15: 12 | J15: =SUM(D15:I15) -> 0
... A33: 30 | J33: =SUM(D33:I33) -> 0

Sheet 4. Scoring
A1: Institutional Income per FTE (PPP-USD) — Scoring
A2: Income per Staff = Total PPP-USD Income ÷ Staff FTE | Z-scored | Higher = better
A3: S.No. | B3: University Name | C3: Country | D3: Total Income (PPP-USD) | E3: Academic Staff FTE | F3: Income per Staff (PPP-USD) | G3: Z-Score | H3: Normalized Score (0–100) | I3: Reporting Year
A4: 1 | D4: ='2. PPP Conversion'!F4 -> 0 | E4: ='3. Staff FTE'!J4 -> 0 | F4: =IF(E4>0,D4/E4,0) -> 0 | G4: =IFERROR((F4-AVERAGE($F$4:$F$33))/STDEV($F$4:$F$33),0) -> 0 | H4: =IFERROR(IF(MAX($F$4:$F$33)-MIN($F$4:$F$33)>0,(F4-MIN($F$4:$F$33))/(MAX($F$4:$F$33)-MIN($F$4:$F$33))*100,0),0) -> 0
A5: 2 | D5: ='2. PPP Conversion'!F5 -> 0 | E5: ='3. Staff FTE'!J5 -> 0 | F5: =IF(E5>0,D5/E5,0) -> 0 | G5: =IFERROR((F5-AVERAGE($F$4:$F$33))/STDEV($F$4:$F$33),0) -> 0 | H5: =IFERROR(IF(MAX($F$4:$F$33)-MIN($F$4:$F$33)>0,(F5-MIN($F$4:$F$33))/(MAX($F$4:$F$33)-MIN($F$4:$F$33))*100,0),0) -> 0
A6: 3 | D6: ='2. PPP Conversion'!F6 -> 0 | E6: ='3. Staff FTE'!J6 -> 0 | F6: =IF(E6>0,D6/E6,0) -> 0 | G6: =IFERROR((F6-AVERAGE($F$4:$F$33))/STDEV($F$4:$F$33),0) -> 0 | H6: =IFERROR(IF(MAX($F$4:$F$33)-MIN($F$4:$F$33)>0,(F6-MIN($F$4:$F$33))/(MAX($F$4:$F$33)-MIN($F$4:$F$33))*100,0),0) -> 0
A7: 4 | D7: ='2. PPP Conversion'!F7 -> 0 | E7: ='3. Staff FTE'!J7 -> 0 | F7: =IF(E7>0,D7/E7,0) -> 0 | G7: =IFERROR((F7-AVERAGE($F$4:$F$33))/STDEV($F$4:$F$33),0) -> 0 | H7: =IFERROR(IF(MAX($F$4:$F$33)-MIN($F$4:$F$33)>0,(F7-MIN($F$4:$F$33))/(MAX($F$4:$F$33)-MIN($F$4:$F$33))*100,0),0) -> 0
A8: 5 | D8: ='2. PPP Conversion'!F8 -> 0 | E8: ='3. Staff FTE'!J8 -> 0 | F8: =IF(E8>0,D8/E8,0) -> 0 | G8: =IFERROR((F8-AVERAGE($F$4:$F$33))/STDEV($F$4:$F$33),0) -> 0 | H8: =IFERROR(IF(MAX($F$4:$F$33)-MIN($F$4:$F$33)>0,(F8-MIN($F$4:$F$33))/(MAX($F$4:$F$33)-MIN($F$4:$F$33))*100,0),0) -> 0
A9: 6 | D9: ='2. PPP Conversion'!F9 -> 0 | E9: ='3. Staff FTE'!J9 -> 0 | F9: =IF(E9>0,D9/E9,0) -> 0 | G9: =IFERROR((F9-AVERAGE($F$4:$F$33))/STDEV($F$4:$F$33),0) -> 0 | H9: =IFERROR(IF(MAX($F$4:$F$33)-MIN($F$4:$F$33)>0,(F9-MIN($F$4:$F$33))/(MAX($F$4:$F$33)-MIN($F$4:$F$33))*100,0),0) -> 0
A10: 7 | D10: ='2. PPP Conversion'!F10 -> 0 | E10: ='3. Staff FTE'!J10 -> 0 | F10: =IF(E10>0,D10/E10,0) -> 0 | G10: =IFERROR((F10-AVERAGE($F$4:$F$33))/STDEV($F$4:$F$33),0) -> 0 | H10: =IFERROR(IF(MAX($F$4:$F$33)-MIN($F$4:$F$33)>0,(F10-MIN($F$4:$F$33))/(MAX($F$4:$F$33)-MIN($F$4:$F$33))*100,0),0) -> 0
A11: 8 | D11: ='2. PPP Conversion'!F11 -> 0 | E11: ='3. Staff FTE'!J11 -> 0 | F11: =IF(E11>0,D11/E11,0) -> 0 | G11: =IFERROR((F11-AVERAGE($F$4:$F$33))/STDEV($F$4:$F$33),0) -> 0 | H11: =IFERROR(IF(MAX($F$4:$F$33)-MIN($F$4:$F$33)>0,(F11-MIN($F$4:$F$33))/(MAX($F$4:$F$33)-MIN($F$4:$F$33))*100,0),0) -> 0
A12: 9 | D12: ='2. PPP Conversion'!F12 -> 0 | E12: ='3. Staff FTE'!J12 -> 0 | F12: =IF(E12>0,D12/E12,0) -> 0 | G12: =IFERROR((F12-AVERAGE($F$4:$F$33))/STDEV($F$4:$F$33),0) -> 0 | H12: =IFERROR(IF(MAX($F$4:$F$33)-MIN($F$4:$F$33)>0,(F12-MIN($F$4:$F$33))/(MAX($F$4:$F$33)-MIN($F$4:$F$33))*100,0),0) -> 0
A13: 10 | D13: ='2. PPP Conversion'!F13 -> 0 | E13: ='3. Staff FTE'!J13 -> 0 | F13: =IF(E13>0,D13/E13,0) -> 0 | G13: =IFERROR((F13-AVERAGE($F$4:$F$33))/STDEV($F$4:$F$33),0) -> 0 | H13: =IFERROR(IF(MAX($F$4:$F$33)-MIN($F$4:$F$33)>0,(F13-MIN($F$4:$F$33))/(MAX($F$4:$F$33)-MIN($F$4:$F$33))*100,0),0) -> 0
A14: 11 | D14: ='2. PPP Conversion'!F14 -> 0 | E14: ='3. Staff FTE'!J14 -> 0 | F14: =IF(E14>0,D14/E14,0) -> 0 | G14: =IFERROR((F14-AVERAGE($F$4:$F$33))/STDEV($F$4:$F$33),0) -> 0 | H14: =IFERROR(IF(MAX($F$4:$F$33)-MIN($F$4:$F$33)>0,(F14-MIN($F$4:$F$33))/(MAX($F$4:$F$33)-MIN($F$4:$F$33))*100,0),0) -> 0
A15: 12 | D15: ='2. PPP Conversion'!F15 -> 0 | E15: ='3. Staff FTE'!J15 -> 0 | F15: =IF(E15>0,D15/E15,0) -> 0 | G15: =IFERROR((F15-AVERAGE($F$4:$F$33))/STDEV($F$4:$F$33),0) -> 0 | H15: =IFERROR(IF(MAX($F$4:$F$33)-MIN($F$4:$F$33)>0,(F15-MIN($F$4:$F$33))/(MAX($F$4:$F$33)-MIN($F$4:$F$33))*100,0),0) -> 0
... A33: 30 | D33: ='2. PPP Conversion'!F33 -> 0 | E33: ='3. Staff FTE'!J33 -> 0 | F33: =IF(E33>0,D33/E33,0) -> 0 | G33: =IFERROR((F33-AVERAGE($F$4:$F$33))/STDEV($F$4:$F$33),0) -> 0 | H33: =IFERROR(IF(MAX($F$4:$F$33)-MIN($F$4:$F$33)>0,(F33-MIN($F$4:$F$33))/(MAX($F$4:$F$33)-MIN($F$4:$F$33))*100,0),0) -> 0
A35: Summary Statistics
A36: Average Income per Staff (PPP-USD) | F36: =IF(COUNTA(F4:F33)>0,AVERAGE(F4:F33),0) -> 0
A37: Highest Income per Staff | F37: =MAX(F4:F33) -> 0
A38: Lowest Income per Staff | F38: =MIN(F4:F33) -> 0
A39: Median | F39: =MEDIAN(F4:F33) -> 0
A40: Std Deviation | F40: =IF(COUNTA(F4:F33)>1,STDEV(F4:F33),0) -> 0

Sheet 5. Revenue Diversification
A1: Revenue Diversification Analysis — Source Proportions & Entropy
A2: % share by source | Shannon entropy on revenue mix | More diversified = more sustainable funding
A3: S.No. | B3: University Name | C3: Country | D3: % Govt Grants | E3: % Tuition Fees | F3: % Research Grants | G3: % Industry | H3: % Endowment | I3: % Philanthropy | J3: % Other | K3: Entropy H (bits) | L3: Diversification Tier
A4: 1 | D4: =IFERROR('1. Total Income'!D4/'1. Total Income'!K4*100,0) -> 0 | E4: =IFERROR('1. Total Income'!E4/'1. Total Income'!K4*100,0) -> 0 | F4: =IFERROR('1. Total Income'!F4/'1. Total Income'!K4*100,0) -> 0 | G4: =IFERROR('1. Total Income'!G4/'1. Total Income'!K4*100,0) -> 0 | H4: =IFERROR('1. Total Income'!H4/'1. Total Income'!K4*100,0) -> 0 | I4: =IFERROR('1. Total Income'!I4/'1. Total Income'!K4*100,0) -> 0 | J4: =IFERROR('1. Total Income'!J4/'1. Total Income'!K4*100,0) -> 0 | K4: =IFERROR(-SUMPRODUCT(IF(D4:J4>0,(D4:J4/100)*LOG(D4:J4/100,2),0)),0) -> 0 | L4: =IF(K4>=2.3,"Very High",IF(K4>=1.8,"High",IF(K4>=1.2,"Moderate",IF(K4>=0.6,"Low","Very Low")))) -> Very Low
A5: 2 | D5: =IFERROR('1. Total Income'!D5/'1. Total Income'!K5*100,0) -> 0 | E5: =IFERROR('1. Total Income'!E5/'1. Total Income'!K5*100,0) -> 0 | F5: =IFERROR('1. Total Income'!F5/'1. Total Income'!K5*100,0) -> 0 | G5: =IFERROR('1. Total Income'!G5/'1. Total Income'!K5*100,0) -> 0 | H5: =IFERROR('1. Total Income'!H5/'1. Total Income'!K5*100,0) -> 0 | I5: =IFERROR('1. Total Income'!I5/'1. Total Income'!K5*100,0) -> 0 | J5: =IFERROR('1. Total Income'!J5/'1. Total Income'!K5*100,0) -> 0 | K5: =IFERROR(-SUMPRODUCT(IF(D5:J5>0,(D5:J5/100)*LOG(D5:J5/100,2),0)),0) -> 0 | L5: =IF(K5>=2.3,"Very High",IF(K5>=1.8,"High",IF(K5>=1.2,"Moderate",IF(K5>=0.6,"Low","Very Low")))) -> Very Low
A6: 3 | D6: =IFERROR('1. Total Income'!D6/'1. Total Income'!K6*100,0) -> 0 | E6: =IFERROR('1. Total Income'!E6/'1. Total Income'!K6*100,0) -> 0 | F6: =IFERROR('1. Total Income'!F6/'1. Total Income'!K6*100,0) -> 0 | G6: =IFERROR('1. Total Income'!G6/'1. Total Income'!K6*100,0) -> 0 | H6: =IFERROR('1. Total Income'!H6/'1. Total Income'!K6*100,0) -> 0 | I6: =IFERROR('1. Total Income'!I6/'1. Total Income'!K6*100,0) -> 0 | J6: =IFERROR('1. Total Income'!J6/'1. Total Income'!K6*100,0) -> 0 | K6: =IFERROR(-SUMPRODUCT(IF(D6:J6>0,(D6:J6/100)*LOG(D6:J6/100,2),0)),0) -> 0 | L6: =IF(K6>=2.3,"Very High",IF(K6>=1.8,"High",IF(K6>=1.2,"Moderate",IF(K6>=0.6,"Low","Very Low")))) -> Very Low
A7: 4 | D7: =IFERROR('1. Total Income'!D7/'1. Total Income'!K7*100,0) -> 0 | E7: =IFERROR('1. Total Income'!E7/'1. Total Income'!K7*100,0) -> 0 | F7: =IFERROR('1. Total Income'!F7/'1. Total Income'!K7*100,0) -> 0 | G7: =IFERROR('1. Total Income'!G7/'1. Total Income'!K7*100,0) -> 0 | H7: =IFERROR('1. Total Income'!H7/'1. Total Income'!K7*100,0) -> 0 | I7: =IFERROR('1. Total Income'!I7/'1. Total Income'!K7*100,0) -> 0 | J7: =IFERROR('1. Total Income'!J7/'1. Total Income'!K7*100,0) -> 0 | K7: =IFERROR(-SUMPRODUCT(IF(D7:J7>0,(D7:J7/100)*LOG(D7:J7/100,2),0)),0) -> 0 | L7: =IF(K7>=2.3,"Very High",IF(K7>=1.8,"High",IF(K7>=1.2,"Moderate",IF(K7>=0.6,"Low","Very Low")))) -> Very Low
A8: 5 | D8: =IFERROR('1. Total Income'!D8/'1. Total Income'!K8*100,0) -> 0 | E8: =IFERROR('1. Total Income'!E8/'1. Total Income'!K8*100,0) -> 0 | F8: =IFERROR('1. Total Income'!F8/'1. Total Income'!K8*100,0) -> 0 | G8: =IFERROR('1. Total Income'!G8/'1. Total Income'!K8*100,0) -> 0 | H8: =IFERROR('1. Total Income'!H8/'1. Total Income'!K8*100,0) -> 0 | I8: =IFERROR('1. Total Income'!I8/'1. Total Income'!K8*100,0) -> 0 | J8: =IFERROR('1. Total Income'!J8/'1. Total Income'!K8*100,0) -> 0 | K8: =IFERROR(-SUMPRODUCT(IF(D8:J8>0,(D8:J8/100)*LOG(D8:J8/100,2),0)),0) -> 0 | L8: =IF(K8>=2.3,"Very High",IF(K8>=1.8,"High",IF(K8>=1.2,"Moderate",IF(K8>=0.6,"Low","Very Low")))) -> Very Low
A9: 6 | D9: =IFERROR('1. Total Income'!D9/'1. Total Income'!K9*100,0) -> 0 | E9: =IFERROR('1. Total Income'!E9/'1. Total Income'!K9*100,0) -> 0 | F9: =IFERROR('1. Total Income'!F9/'1. Total Income'!K9*100,0) -> 0 | G9: =IFERROR('1. Total Income'!G9/'1. Total Income'!K9*100,0) -> 0 | H9: =IFERROR('1. Total Income'!H9/'1. Total Income'!K9*100,0) -> 0 | I9: =IFERROR('1. Total Income'!I9/'1. Total Income'!K9*100,0) -> 0 | J9: =IFERROR('1. Total Income'!J9/'1. Total Income'!K9*100,0) -> 0 | K9: =IFERROR(-SUMPRODUCT(IF(D9:J9>0,(D9:J9/100)*LOG(D9:J9/100,2),0)),0) -> 0 | L9: =IF(K9>=2.3,"Very High",IF(K9>=1.8,"High",IF(K9>=1.2,"Moderate",IF(K9>=0.6,"Low","Very Low")))) -> Very Low
A10: 7 | D10: =IFERROR('1. Total Income'!D10/'1. Total Income'!K10*100,0) -> 0 | E10: =IFERROR('1. Total Income'!E10/'1. Total Income'!K10*100,0) -> 0 | F10: =IFERROR('1. Total Income'!F10/'1. Total Income'!K10*100,0) -> 0 | G10: =IFERROR('1. Total Income'!G10/'1. Total Income'!K10*100,0) -> 0 | H10: =IFERROR('1. Total Income'!H10/'1. Total Income'!K10*100,0) -> 0 | I10: =IFERROR('1. Total Income'!I10/'1. Total Income'!K10*100,0) -> 0 | J10: =IFERROR('1. Total Income'!J10/'1. Total Income'!K10*100,0) -> 0 | K10: =IFERROR(-SUMPRODUCT(IF(D10:J10>0,(D10:J10/100)*LOG(D10:J10/100,2),0)),0) -> 0 | L10: =IF(K10>=2.3,"Very High",IF(K10>=1.8,"High",IF(K10>=1.2,"Moderate",IF(K10>=0.6,"Low","Very Low")))) -> Very Low
A11: 8 | D11: =IFERROR('1. Total Income'!D11/'1. Total Income'!K11*100,0) -> 0 | E11: =IFERROR('1. Total Income'!E11/'1. Total Income'!K11*100,0) -> 0 | F11: =IFERROR('1. Total Income'!F11/'1. Total Income'!K11*100,0) -> 0 | G11: =IFERROR('1. Total Income'!G11/'1. Total Income'!K11*100,0) -> 0 | H11: =IFERROR('1. Total Income'!H11/'1. Total Income'!K11*100,0) -> 0 | I11: =IFERROR('1. Total Income'!I11/'1. Total Income'!K11*100,0) -> 0 | J11: =IFERROR('1. Total Income'!J11/'1. Total Income'!K11*100,0) -> 0 | K11: =IFERROR(-SUMPRODUCT(IF(D11:J11>0,(D11:J11/100)*LOG(D11:J11/100,2),0)),0) -> 0 | L11: =IF(K11>=2.3,"Very High",IF(K11>=1.8,"High",IF(K11>=1.2,"Moderate",IF(K11>=0.6,"Low","Very Low")))) -> Very Low
A12: 9 | D12: =IFERROR('1. Total Income'!D12/'1. Total Income'!K12*100,0) -> 0 | E12: =IFERROR('1. Total Income'!E12/'1. Total Income'!K12*100,0) -> 0 | F12: =IFERROR('1. Total Income'!F12/'1. Total Income'!K12*100,0) -> 0 | G12: =IFERROR('1. Total Income'!G12/'1. Total Income'!K12*100,0) -> 0 | H12: =IFERROR('1. Total Income'!H12/'1. Total Income'!K12*100,0) -> 0 | I12: =IFERROR('1. Total Income'!I12/'1. Total Income'!K12*100,0) -> 0 | J12: =IFERROR('1. Total Income'!J12/'1. Total Income'!K12*100,0) -> 0 | K12: =IFERROR(-SUMPRODUCT(IF(D12:J12>0,(D12:J12/100)*LOG(D12:J12/100,2),0)),0) -> 0 | L12: =IF(K12>=2.3,"Very High",IF(K12>=1.8,"High",IF(K12>=1.2,"Moderate",IF(K12>=0.6,"Low","Very Low")))) -> Very Low
A13: 10 | D13: =IFERROR('1. Total Income'!D13/'1. Total Income'!K13*100,0) -> 0 | E13: =IFERROR('1. Total Income'!E13/'1. Total Income'!K13*100,0) -> 0 | F13: =IFERROR('1. Total Income'!F13/'1. Total Income'!K13*100,0) -> 0 | G13: =IFERROR('1. Total Income'!G13/'1. Total Income'!K13*100,0) -> 0 | H13: =IFERROR('1. Total Income'!H13/'1. Total Income'!K13*100,0) -> 0 | I13: =IFERROR('1. Total Income'!I13/'1. Total Income'!K13*100,0) -> 0 | J13: =IFERROR('1. Total Income'!J13/'1. Total Income'!K13*100,0) -> 0 | K13: =IFERROR(-SUMPRODUCT(IF(D13:J13>0,(D13:J13/100)*LOG(D13:J13/100,2),0)),0) -> 0 | L13: =IF(K13>=2.3,"Very High",IF(K13>=1.8,"High",IF(K13>=1.2,"Moderate",IF(K13>=0.6,"Low","Very Low")))) -> Very Low
A14: 11 | D14: =IFERROR('1. Total Income'!D14/'1. Total Income'!K14*100,0) -> 0 | E14: =IFERROR('1. Total Income'!E14/'1. Total Income'!K14*100,0) -> 0 | F14: =IFERROR('1. Total Income'!F14/'1. Total Income'!K14*100,0) -> 0 | G14: =IFERROR('1. Total Income'!G14/'1. Total Income'!K14*100,0) -> 0 | H14: =IFERROR('1. Total Income'!H14/'1. Total Income'!K14*100,0) -> 0 | I14: =IFERROR('1. Total Income'!I14/'1. Total Income'!K14*100,0) -> 0 | J14: =IFERROR('1. Total Income'!J14/'1. Total Income'!K14*100,0) -> 0 | K14: =IFERROR(-SUMPRODUCT(IF(D14:J14>0,(D14:J14/100)*LOG(D14:J14/100,2),0)),0) -> 0 | L14: =IF(K14>=2.3,"Very High",IF(K14>=1.8,"High",IF(K14>=1.2,"Moderate",IF(K14>=0.6,"Low","Very Low")))) -> Very Low
A15: 12 | D15: =IFERROR('1. Total Income'!D15/'1. Total Income'!K15*100,0) -> 0 | E15: =IFERROR('1. Total Income'!E15/'1. Total Income'!K15*100,0) -> 0 | F15: =IFERROR('1. Total Income'!F15/'1. Total Income'!K15*100,0) -> 0 | G15: =IFERROR('1. Total Income'!G15/'1. Total Income'!K15*100,0) -> 0 | H15: =IFERROR('1. Total Income'!H15/'1. Total Income'!K15*100,0) -> 0 | I15: =IFERROR('1. Total Income'!I15/'1. Total Income'!K15*100,0) -> 0 | J15: =IFERROR('1. Total Income'!J15/'1. Total Income'!K15*100,0) -> 0 | K15: =IFERROR(-SUMPRODUCT(IF(D15:J15>0,(D15:J15/100)*LOG(D15:J15/100,2),0)),0) -> 0 | L15: =IF(K15>=2.3,"Very High",IF(K15>=1.8,"High",IF(K15>=1.2,"Moderate",IF(K15>=0.6,"Low","Very Low")))) -> Very Low
... A33: 30 | D33: =IFERROR('1. Total Income'!D33/'1. Total Income'!K33*100,0) -> 0 | E33: =IFERROR('1. Total Income'!E33/'1. Total Income'!K33*100,0) -> 0 | F33: =IFERROR('1. Total Income'!F33/'1. Total Income'!K33*100,0) -> 0 | G33: =IFERROR('1. Total Income'!G33/'1. Total Income'!K33*100,0) -> 0 | H33: =IFERROR('1. Total Income'!H33/'1. Total Income'!K33*100,0) -> 0 | I33: =IFERROR('1. Total Income'!I33/'1. Total Income'!K33*100,0) -> 0 | J33: =IFERROR('1. Total Income'!J33/'1. Total Income'!K33*100,0) -> 0 | K33: =IFERROR(-SUMPRODUCT(IF(D33:J33>0,(D33:J33/100)*LOG(D33:J33/100,2),0)),0) -> 0 | L33: =IF(K33>=2.3,"Very High",IF(K33>=1.8,"High",IF(K33>=1.2,"Moderate",IF(K33>=0.6,"Low","Very Low")))) -> Very Low

Sheet 6. YoY Trend
A1: Institutional Income — 5-Year Trend (PPP-USD per Staff)
A2: Track income growth trajectory | CAGR calculation
A3: S.No. | B3: University Name | C3: Country | D3: Year 1 (Income/FTE) | E3: Year 2 | F3: Year 3 | G3: Year 4 | H3: Year 5 (Current) | I3: CAGR (%) | J3: 5-Year Absolute Growth (%) | K3: Trend
A4: 1 | I4: =IFERROR(IF(AND(D4>0,H4>0),(H4/D4)^(1/4)-1,0)*100,0) -> 0 | J4: =IFERROR(IF(D4>0,(H4-D4)/D4*100,0),0) -> 0 | K4: =IF(I4>=10,"Strong Growth",IF(I4>=3,"Moderate Growth",IF(I4>=0,"Stable","Declining"))) -> Stable
A5: 2 | I5: =IFERROR(IF(AND(D5>0,H5>0),(H5/D5)^(1/4)-1,0)*100,0) -> 0 | J5: =IFERROR(IF(D5>0,(H5-D5)/D5*100,0),0) -> 0 | K5: =IF(I5>=10,"Strong Growth",IF(I5>=3,"Moderate Growth",IF(I5>=0,"Stable","Declining"))) -> Stable
A6: 3 | I6: =IFERROR(IF(AND(D6>0,H6>0),(H6/D6)^(1/4)-1,0)*100,0) -> 0 | J6: =IFERROR(IF(D6>0,(H6-D6)/D6*100,0),0) -> 0 | K6: =IF(I6>=10,"Strong Growth",IF(I6>=3,"Moderate Growth",IF(I6>=0,"Stable","Declining"))) -> Stable
A7: 4 | I7: =IFERROR(IF(AND(D7>0,H7>0),(H7/D7)^(1/4)-1,0)*100,0) -> 0 | J7: =IFERROR(IF(D7>0,(H7-D7)/D7*100,0),0) -> 0 | K7: =IF(I7>=10,"Strong Growth",IF(I7>=3,"Moderate Growth",IF(I7>=0,"Stable","Declining"))) -> Stable
A8: 5 | I8: =IFERROR(IF(AND(D8>0,H8>0),(H8/D8)^(1/4)-1,0)*100,0) -> 0 | J8: =IFERROR(IF(D8>0,(H8-D8)/D8*100,0),0) -> 0 | K8: =IF(I8>=10,"Strong Growth",IF(I8>=3,"Moderate Growth",IF(I8>=0,"Stable","Declining"))) -> Stable
A9: 6 | I9: =IFERROR(IF(AND(D9>0,H9>0),(H9/D9)^(1/4)-1,0)*100,0) -> 0 | J9: =IFERROR(IF(D9>0,(H9-D9)/D9*100,0),0) -> 0 | K9: =IF(I9>=10,"Strong Growth",IF(I9>=3,"Moderate Growth",IF(I9>=0,"Stable","Declining"))) -> Stable
A10: 7 | I10: =IFERROR(IF(AND(D10>0,H10>0),(H10/D10)^(1/4)-1,0)*100,0) -> 0 | J10: =IFERROR(IF(D10>0,(H10-D10)/D10*100,0),0) -> 0 | K10: =IF(I10>=10,"Strong Growth",IF(I10>=3,"Moderate Growth",IF(I10>=0,"Stable","Declining"))) -> Stable
A11: 8 | I11: =IFERROR(IF(AND(D11>0,H11>0),(H11/D11)^(1/4)-1,0)*100,0) -> 0 | J11: =IFERROR(IF(D11>0,(H11-D11)/D11*100,0),0) -> 0 | K11: =IF(I11>=10,"Strong Growth",IF(I11>=3,"Moderate Growth",IF(I11>=0,"Stable","Declining"))) -> Stable
A12: 9 | I12: =IFERROR(IF(AND(D12>0,H12>0),(H12/D12)^(1/4)-1,0)*100,0) -> 0 | J12: =IFERROR(IF(D12>0,(H12-D12)/D12*100,0),0) -> 0 | K12: =IF(I12>=10,"Strong Growth",IF(I12>=3,"Moderate Growth",IF(I12>=0,"Stable","Declining"))) -> Stable
A13: 10 | I13: =IFERROR(IF(AND(D13>0,H13>0),(H13/D13)^(1/4)-1,0)*100,0) -> 0 | J13: =IFERROR(IF(D13>0,(H13-D13)/D13*100,0),0) -> 0 | K13: =IF(I13>=10,"Strong Growth",IF(I13>=3,"Moderate Growth",IF(I13>=0,"Stable","Declining"))) -> Stable
A14: 11 | I14: =IFERROR(IF(AND(D14>0,H14>0),(H14/D14)^(1/4)-1,0)*100,0) -> 0 | J14: =IFERROR(IF(D14>0,(H14-D14)/D14*100,0),0) -> 0 | K14: =IF(I14>=10,"Strong Growth",IF(I14>=3,"Moderate Growth",IF(I14>=0,"Stable","Declining"))) -> Stable
A15: 12 | I15: =IFERROR(IF(AND(D15>0,H15>0),(H15/D15)^(1/4)-1,0)*100,0) -> 0 | J15: =IFERROR(IF(D15>0,(H15-D15)/D15*100,0),0) -> 0 | K15: =IF(I15>=10,"Strong Growth",IF(I15>=3,"Moderate Growth",IF(I15>=0,"Stable","Declining"))) -> Stable
... A33: 30 | I33: =IFERROR(IF(AND(D33>0,H33>0),(H33/D33)^(1/4)-1,0)*100,0) -> 0 | J33: =IFERROR(IF(D33>0,(H33-D33)/D33*100,0),0) -> 0 | K33: =IF(I33>=10,"Strong Growth",IF(I33>=3,"Moderate Growth",IF(I33>=0,"Stable","Declining"))) -> Stable

Sheet 7. Income Rules
A1: Income Counting Rules — Inclusions & Exclusions per THE Definition
A2: What counts as 'institutional income' for this indicator
A3: # | B3: Category | C3: Revenue Item | D3: Include / Exclude | E3: Notes
A4: 1 | B4: Operating | C4: Government block grant / recurrent funding | D4: Include | E4: Core government allocation
A5: 2 | B5: Operating | C5: Government performance-based funding | D5: Include | E5: Outcome-linked grants
A6: 3 | B6: Operating | C6: Tuition fees (domestic students) | D6: Include | E6: All programme levels
A7: 4 | B7: Operating | C7: Tuition fees (international students) | D7: Include | E7: All programme levels
A8: 5 | B8: Operating | C8: Student accommodation / housing revenue | D8: Include | E8: If part of university accounts
A9: 6 | B9: Research | C9: Research grants (government agencies) | D9: Include | E9: Competitive & block research grants
A10: 7 | B10: Research | C10: Research grants (international agencies) | D10: Include | E10: EU, UNDP, World Bank, bilateral
A11: 8 | B11: Research | C11: Industry-sponsored research income | D11: Include | E11: Contract research, co-funded R&D
A12: 9 | B12: Commercial | C12: Consultancy & technical services revenue | D12: Include | E12: Applied knowledge services
A13: 10 | B13: Commercial | C13: Executive education / CPD revenue | D13: Include | E13: Fee-based professional programmes
A14: 11 | B14: Commercial | C14: Facility rental / conference income | D14: Include | E14: Campus-generated revenue
A15: 12 | B15: Investment | C15: Endowment investment returns | D15: Include | E15: Annual yield, not principal
... A23: 20 | B23: Transfer | C23: Government loans (to be repaid) | D23: Exclude | E23: Not revenue; liability

Sheet 8. Revenue Action Plan
A1: Revenue Growth & Diversification — Strategic Action Plan
A2: Actions to increase institutional income per FTE | Short & medium-term strategies
A3: # | B3: University Name | C3: Action Item | D3: Phase | E3: Status | F3: Target Date | G3: Remarks
A4: 1 | C4: Audit current revenue streams and identify growth opportunities | D4: 1 (0–6mo)
A5: 2 | C5: Establish institutional advancement / fundraising office | D5: 1 (0–6mo)
A6: 3 | C6: Launch alumni engagement programme for philanthropic giving | D6: 1 (0–6mo)
A7: 4 | C7: Maximize government grant capture — competitive proposal training | D7: 1 (0–6mo)
A8: 5 | C8: Pursue industry partnerships for sponsored R&D income growth | D8: 2 (6–18mo)
A9: 6 | C9: Launch fee-based executive education / CPD programmes | D9: 2 (6–18mo)
A10: 7 | C10: Establish consultancy & technical services unit | D10: 2 (6–18mo)
A11: 8 | C11: Grow international student enrolment (higher-fee cohort) | D11: 2 (6–18mo)
A12: 9 | C12: Create endowment fund with target corpus and annual yield | D12: 2 (6–18mo)
A13: 10 | C13: Develop CSR-to-research pipeline with corporate partners | D13: 2 (6–18mo)
A14: 11 | C14: Build commercial conference / facility rental business | D14: 2 (6–18mo)
A15: 12 | C15: Diversify into online / hybrid programmes generating fee revenue | D15: 3 (18–36mo)
... A17: 14 | C17: Achieve revenue entropy >2.0 bits (strong diversification) | D17: 3 (18–36mo)
A19: Progress Summary
A20: Completed | D20: =COUNTIF(E4:E17,"Done") -> 0
A21: In Progress | D21: =COUNTIF(E4:E17,"IP") -> 0
A22: Completion (%) | D22: =IFERROR(COUNTIF(E4:E17,"Done")/14*100,0) -> 0

Sheet 9. Benchmarking
A1: Benchmarking — Institutional Income (PPP-Scaled per FTE)
A3: S.No. | B3: University / Benchmark | C3: Total Income (PPP-USD) | D3: Staff FTE | E3: Income/FTE (PPP-USD) | F3: Score (0–100) | G3: Peer Group
A4: 1 | B4: Your Institution | G4: Target
A5: 2 | B5: Global Top 10 Average | G5: Aspirational
A6: 3 | B6: National Average | G6: National
A7: 4 | B7: Peer Group Average | G7: Peer
A8: 1
A9: 2
A10: 3
A11: 4
A12: 5
A13: 6
A14: 7
A15: 8
A16: 9
A17: 10
A18: 11
A19: 12
... A22: 15

Sheet 10. Risk Assessment
A1: Institutional Income — Risk Assessment & Mitigation
A3: # | B3: Risk | C3: Level | D3: Impact | E3: Mitigation | F3: Owner
A4: 1 | B4: Over-reliance on single revenue source | C4: 🟡 Medium | D4: Low entropy; vulnerable to funding cuts; score stagnates | E4: Diversify across 5+ sources; target entropy >2.0 bits
A5: 2 | B5: Government funding reduction | C5: 🟡 Medium | D5: Block grant cut reduces total income | E5: Grow alternative revenue: fees, industry, philanthropy, endowment
A6: 3 | B6: PPP rate fluctuation | C6: 🟢 Low | D6: Year-to-year PPP changes affect comparability | E6: Use consistent World Bank PPP rate; document year and source
A7: 4 | B7: Incorrect PPP factor used | C7: 🔴 High | D7: Income inflated or deflated vs peers; rank impact | E7: Verify PPP against World Bank databank for exact year; double-check
A8: 5 | B8: Capital income included in revenue | C8: 🔴 High | D8: One-time grants inflate income; audit risk | E8: Exclude capital grants, asset sales, endowment principal per THE rules
A9: 6 | B9: Internal transfers double-counted | C9: 🔴 High | D9: Inflated total income; audit failure | E9: Eliminate inter-entity transfers in consolidation
A10: 7 | B10: Staff FTE inconsistency across indicators | C10: 🔴 High | D10: Different FTE for income/staff-ratio/doctoral indicators | E10: Use SAME Academic Staff FTE across all Teaching sub-indicators
A11: 8 | B11: Revenue reporting on accrual vs cash basis | C11: 🟡 Medium | D11: Timing differences affect year comparison | E11: Document accounting basis; use same basis consistently

Sheet 11. Data Quality Audit
A1: Institutional Income (PPP) — Data Quality & Audit Checklist
A2: Validation checks for this indicator (2.5% of total WUR score)
A3: # | B3: Quality Check | C3: Description | D3: Status (✓/✗/IP) | E3: Date | F3: Reviewer
A4: 1 | B4: Audited accounts verification | C4: All income figures verified against audited institutional financial statements
A5: 2 | B5: Revenue source completeness | C5: All 7 revenue categories populated; no major source omitted
A6: 3 | B6: Capital income exclusion | C6: Capital grants, asset sale proceeds, endowment principal excluded from total
A7: 4 | B7: Internal transfer elimination | C7: Inter-entity transfers removed to prevent double-counting
A8: 5 | B8: Hospital income treatment | C8: Clinical/hospital revenue included only if consolidated in university accounts
A9: 6 | B9: PPP rate accuracy | C9: PPP conversion factor matches World Bank databank for the exact submission year
A10: 7 | B10: PPP rate source documentation | C10: Year, source, and specific rate documented in submission
A11: 8 | B11: Local currency consistency | C11: All revenue items in same local currency before PPP conversion
A12: 9 | B12: Academic Staff FTE consistency | C12: SAME Staff FTE used here AND in Staff-to-Student Ratio (4.5%) AND Doctorates-per-Staff (5.5%)
A13: 10 | B13: FTE THE-compliant | C13: Staff FTE follows THE definition; research-only, admin, technical excluded
A14: 11 | B14: Income per FTE calculation | C14: Total PPP-USD ÷ Staff FTE verified independently by 2 reviewers
A15: 12 | B15: Source breakdown reconciliation | C15: Sum of 7 revenue categories = total income (within ±1% tolerance)
... A23: 20 | B23: Reproducibility test | C23: Income per FTE independently reproducible from audited accounts + HR records within ±2%
